[{"instances": "auto1", "configurations": 0, "value": [[99, 160], [155, 586]]}, {"instances": "auto1", "configurations": 1, "value": [[99, 160], [155, 586]]}, {"instances": "auto1", "configurations": 2, "value": [[99, 160], [155, 586]]}, {"instances": "auto1", "configurations": 3, "value": [[99, 160], [155, 586]]}, {"instances": "auto1", "configurations": 4, "value": [[95, 164], [154, 587]]}, {"instances": "auto1", "configurations": 5, "value": [[95, 164], [154, 587]]}, {"instances": "auto1", "configurations": 6, "value": [[86, 173], [151, 590]]}, {"instances": "auto1", "configurations": 7, "value": [[86, 173], [151, 590]]}, {"instances": "auto1", "configurations": 8, "value": [[85, 174], [173, 568]]}, {"instances": "auto1", "configurations": 9, "value": [[85, 174], [173, 568]]}, {"instances": "auto1", "configurations": 10, "value": [[97, 162], [154, 587]]}, {"instances": "auto1", "configurations": 11, "value": [[97, 162], [154, 587]]}, {"instances": "auto1", "configurations": 12, "value": [[155, 104], [275, 466]]}, {"instances": "auto1", "configurations": 13, "value": [[99, 160], [155, 586]]}, {"instances": "auto1", "configurations": 14, "value": [[155, 104], [275, 466]]}, {"instances": "auto1", "configurations": 15, "value": [[99, 160], [155, 586]]}, {"instances": "auto1", "configurations": 16, "value": [[145, 114], [272, 469]]}, {"instances": "auto1", "configurations": 17, "value": [[95, 164], [154, 587]]}, {"instances": "auto1", "configurations": 18, "value": [[139, 120], [286, 455]]}, {"instances": "auto1", "configurations": 19, "value": [[118, 141], [217, 524]]}, {"instances": "auto1", "configurations": 20, "value": [[126, 133], [294, 447]]}, {"instances": "auto1", "configurations": 21, "value": [[102, 157], [219, 522]]}, {"instances": "auto1", "configurations": 22, "value": [[146, 113], [275, 466]]}, {"instances": "auto1", "configurations": 23, "value": [[97, 162], [154, 587]]}, {"instances": "auto1", "configurations": 24, "value": [[76, 183], [96, 645]]}, {"instances": "auto1", "configurations": 25, "value": [[79, 180], [97, 644]]}, {"instances": "auto1", "configurations": 26, "value": [[76, 183], [95, 646]]}, {"instances": "auto1", "configurations": 27, "value": [[76, 183], [95, 646]]}, {"instances": "auto1", "configurations": 28, "value": [[71, 188], [86, 655]]}, {"instances": "auto1", "configurations": 29, "value": [[73, 186], [90, 651]]}, {"instances": "auto1", "configurations": 30, "value": [[72, 187], [100, 641]]}, {"instances": "auto1", "configurations": 31, "value": [[74, 185], [110, 631]]}, {"instances": "auto1", "configurations": 32, "value": [[72, 187], [113, 628]]}, {"instances": "auto1", "configurations": 33, "value": [[74, 185], [113, 628]]}, {"instances": "auto1", "configurations": 34, "value": [[73, 186], [84, 657]]}, {"instances": "auto1", "configurations": 35, "value": [[75, 184], [89, 652]]}, {"instances": "auto1", "configurations": 36, "value": [[100, 159], [158, 583]]}, {"instances": "auto1", "configurations": 37, "value": [[74, 185], [95, 646]]}, {"instances": "auto1", "configurations": 38, "value": [[100, 159], [158, 583]]}, {"instances": "auto1", "configurations": 39, "value": [[75, 184], [97, 644]]}, {"instances": "auto1", "configurations": 40, "value": [[94, 165], [158, 583]]}, {"instances": "auto1", "configurations": 41, "value": [[71, 188], [92, 649]]}, {"instances": "auto1", "configurations": 42, "value": [[96, 163], [163, 578]]}, {"instances": "auto1", "configurations": 43, "value": [[76, 183], [116, 625]]}, {"instances": "auto1", "configurations": 44, "value": [[95, 164], [186, 555]]}, {"instances": "auto1", "configurations": 45, "value": [[77, 182], [122, 619]]}, {"instances": "auto1", "configurations": 46, "value": [[97, 162], [161, 580]]}, {"instances": "auto1", "configurations": 47, "value": [[73, 186], [93, 648]]}, {"instances": "auto1", "configurations": 48, "value": [[68, 191], [71, 670]]}, {"instances": "auto1", "configurations": 49, "value": [[72, 187], [66, 675]]}, {"instances": "auto1", "configurations": 50, "value": [[68, 191], [72, 669]]}, {"instances": "auto1", "configurations": 51, "value": [[68, 191], [72, 669]]}, {"instances": "auto1", "configurations": 52, "value": [[68, 191], [65, 676]]}, {"instances": "auto1", "configurations": 53, "value": [[71, 188], [64, 677]]}, {"instances": "auto1", "configurations": 54, "value": [[55, 204], [71, 670]]}, {"instances": "auto1", "configurations": 55, "value": [[62, 197], [75, 666]]}, {"instances": "auto1", "configurations": 56, "value": [[59, 200], [97, 644]]}, {"instances": "auto1", "configurations": 57, "value": [[61, 198], [97, 644]]}, {"instances": "auto1", "configurations": 58, "value": [[67, 192], [60, 681]]}, {"instances": "auto1", "configurations": 59, "value": [[70, 189], [58, 683]]}, {"instances": "auto1", "configurations": 60, "value": [[89, 170], [115, 626]]}, {"instances": "auto1", "configurations": 61, "value": [[63, 196], [67, 674]]}, {"instances": "auto1", "configurations": 62, "value": [[89, 170], [115, 626]]}, {"instances": "auto1", "configurations": 63, "value": [[65, 194], [68, 673]]}, {"instances": "auto1", "configurations": 64, "value": [[87, 172], [111, 630]]}, {"instances": "auto1", "configurations": 65, "value": [[65, 194], [67, 674]]}, {"instances": "auto1", "configurations": 66, "value": [[86, 173], [103, 638]]}, {"instances": "auto1", "configurations": 67, "value": [[67, 192], [70, 671]]}, {"instances": "auto1", "configurations": 68, "value": [[76, 183], [132, 609]]}, {"instances": "auto1", "configurations": 69, "value": [[62, 197], [87, 654]]}, {"instances": "auto1", "configurations": 70, "value": [[88, 171], [111, 630]]}, {"instances": "auto1", "configurations": 71, "value": [[68, 191], [63, 678]]}, {"instances": "auto1", "configurations": 72, "value": [[58, 201], [56, 685]]}, {"instances": "auto1", "configurations": 73, "value": [[62, 197], [54, 687]]}, {"instances": "auto1", "configurations": 74, "value": [[58, 201], [57, 684]]}, {"instances": "auto1", "configurations": 75, "value": [[59, 200], [58, 683]]}, {"instances": "auto1", "configurations": 76, "value": [[56, 203], [56, 685]]}, {"instances": "auto1", "configurations": 77, "value": [[61, 198], [55, 686]]}, {"instances": "auto1", "configurations": 78, "value": [[53, 206], [45, 696]]}, {"instances": "auto1", "configurations": 79, "value": [[57, 202], [49, 692]]}, {"instances": "auto1", "configurations": 80, "value": [[48, 211], [67, 674]]}, {"instances": "auto1", "configurations": 81, "value": [[50, 209], [67, 674]]}, {"instances": "auto1", "configurations": 82, "value": [[58, 201], [52, 689]]}, {"instances": "auto1", "configurations": 83, "value": [[63, 196], [52, 689]]}, {"instances": "auto1", "configurations": 84, "value": [[73, 186], [94, 647]]}, {"instances": "auto1", "configurations": 85, "value": [[58, 201], [55, 686]]}, {"instances": "auto1", "configurations": 86, "value": [[73, 186], [94, 647]]}, {"instances": "auto1", "configurations": 87, "value": [[60, 199], [53, 688]]}, {"instances": "auto1", "configurations": 88, "value": [[76, 183], [86, 655]]}, {"instances": "auto1", "configurations": 89, "value": [[60, 199], [47, 694]]}, {"instances": "auto1", "configurations": 90, "value": [[75, 184], [70, 671]]}, {"instances": "auto1", "configurations": 91, "value": [[62, 197], [52, 689]]}, {"instances": "auto1", "configurations": 92, "value": [[71, 188], [118, 623]]}, {"instances": "auto1", "configurations": 93, "value": [[60, 199], [86, 655]]}, {"instances": "auto1", "configurations": 94, "value": [[85, 174], [88, 653]]}, {"instances": "auto1", "configurations": 95, "value": [[64, 195], [50, 691]]}, {"instances": "auto1", "configurations": 96, "value": [[47, 212], [46, 695]]}, {"instances": "auto1", "configurations": 97, "value": [[56, 203], [45, 696]]}, {"instances": "auto1", "configurations": 98, "value": [[48, 211], [45, 696]]}, {"instances": "auto1", "configurations": 99, "value": [[52, 207], [44, 697]]}, {"instances": "auto1", "configurations": 100, "value": [[47, 212], [37, 704]]}, {"instances": "auto1", "configurations": 101, "value": [[56, 203], [37, 704]]}, {"instances": "auto1", "configurations": 102, "value": [[51, 208], [41, 700]]}, {"instances": "auto1", "configurations": 103, "value": [[61, 198], [44, 697]]}, {"instances": "auto1", "configurations": 104, "value": [[44, 215], [47, 694]]}, {"instances": "auto1", "configurations": 105, "value": [[46, 213], [47, 694]]}, {"instances": "auto1", "configurations": 106, "value": [[53, 206], [41, 700]]}, {"instances": "auto1", "configurations": 107, "value": [[60, 199], [39, 702]]}, {"instances": "auto1", "configurations": 108, "value": [[64, 195], [79, 662]]}, {"instances": "auto1", "configurations": 109, "value": [[52, 207], [43, 698]]}, {"instances": "auto1", "configurations": 110, "value": [[65, 194], [79, 662]]}, {"instances": "auto1", "configurations": 111, "value": [[54, 205], [45, 696]]}, {"instances": "auto1", "configurations": 112, "value": [[66, 193], [58, 683]]}, {"instances": "auto1", "configurations": 113, "value": [[55, 204], [30, 711]]}, {"instances": "auto1", "configurations": 114, "value": [[58, 201], [54, 687]]}, {"instances": "auto1", "configurations": 115, "value": [[49, 210], [36, 705]]}, {"instances": "auto1", "configurations": 116, "value": [[41, 218], [68, 673]]}, {"instances": "auto1", "configurations": 117, "value": [[42, 217], [44, 697]]}, {"instances": "auto1", "configurations": 118, "value": [[67, 192], [60, 681]]}, {"instances": "auto1", "configurations": 119, "value": [[57, 202], [37, 704]]}, {"instances": "auto1", "configurations": 120, "value": [[37, 222], [23, 718]]}, {"instances": "auto1", "configurations": 121, "value": [[45, 214], [25, 716]]}, {"instances": "auto1", "configurations": 122, "value": [[37, 222], [23, 718]]}, {"instances": "auto1", "configurations": 123, "value": [[42, 217], [22, 719]]}, {"instances": "auto1", "configurations": 124, "value": [[27, 232], [24, 717]]}, {"instances": "auto1", "configurations": 125, "value": [[40, 219], [25, 716]]}, {"instances": "auto1", "configurations": 126, "value": [[26, 233], [23, 718]]}, {"instances": "auto1", "configurations": 127, "value": [[39, 220], [27, 714]]}, {"instances": "auto1", "configurations": 128, "value": [[26, 233], [19, 722]]}, {"instances": "auto1", "configurations": 129, "value": [[28, 231], [19, 722]]}, {"instances": "auto1", "configurations": 130, "value": [[27, 232], [21, 720]]}, {"instances": "auto1", "configurations": 131, "value": [[39, 220], [23, 718]]}, {"instances": "auto1", "configurations": 132, "value": [[28, 231], [17, 724]]}, {"instances": "auto1", "configurations": 133, "value": [[31, 228], [18, 723]]}, {"instances": "auto1", "configurations": 134, "value": [[27, 232], [18, 723]]}, {"instances": "auto1", "configurations": 135, "value": [[24, 235], [16, 725]]}, {"instances": "auto1", "configurations": 136, "value": [[28, 231], [20, 721]]}, {"instances": "auto1", "configurations": 137, "value": [[34, 225], [20, 721]]}, {"instances": "auto1", "configurations": 138, "value": [[25, 234], [24, 717]]}, {"instances": "auto1", "configurations": 139, "value": [[32, 227], [19, 722]]}, {"instances": "auto1", "configurations": 140, "value": [[34, 225], [26, 715]]}, {"instances": "auto1", "configurations": 141, "value": [[33, 226], [20, 721]]}, {"instances": "auto1", "configurations": 142, "value": [[33, 226], [22, 719]]}, {"instances": "auto1", "configurations": 143, "value": [[39, 220], [20, 721]]}, {"instances": "auto1", "configurations": 144, "value": [[15, 244], [9, 732]]}, {"instances": "auto1", "configurations": 145, "value": [[25, 234], [15, 726]]}, {"instances": "auto1", "configurations": 146, "value": [[15, 244], [9, 732]]}, {"instances": "auto1", "configurations": 147, "value": [[18, 241], [10, 731]]}, {"instances": "auto1", "configurations": 148, "value": [[15, 244], [10, 731]]}, {"instances": "auto1", "configurations": 149, "value": [[27, 232], [15, 726]]}, {"instances": "auto1", "configurations": 150, "value": [[17, 242], [11, 730]]}, {"instances": "auto1", "configurations": 151, "value": [[24, 235], [13, 728]]}, {"instances": "auto1", "configurations": 152, "value": [[34, 225], [24, 717]]}, {"instances": "auto1", "configurations": 153, "value": [[36, 223], [24, 717]]}, {"instances": "auto1", "configurations": 154, "value": [[17, 242], [7, 734]]}, {"instances": "auto1", "configurations": 155, "value": [[30, 229], [15, 726]]}, {"instances": "auto1", "configurations": 156, "value": [[14, 245], [10, 731]]}, {"instances": "auto1", "configurations": 157, "value": [[18, 241], [14, 727]]}, {"instances": "auto1", "configurations": 158, "value": [[14, 245], [10, 731]]}, {"instances": "auto1", "configurations": 159, "value": [[15, 244], [10, 731]]}, {"instances": "auto1", "configurations": 160, "value": [[14, 245], [10, 731]]}, {"instances": "auto1", "configurations": 161, "value": [[18, 241], [12, 729]]}, {"instances": "auto1", "configurations": 162, "value": [[13, 246], [12, 729]]}, {"instances": "auto1", "configurations": 163, "value": [[18, 241], [12, 729]]}, {"instances": "auto1", "configurations": 164, "value": [[16, 243], [12, 729]]}, {"instances": "auto1", "configurations": 165, "value": [[18, 241], [12, 729]]}, {"instances": "auto1", "configurations": 166, "value": [[17, 242], [8, 733]]}, {"instances": "auto1", "configurations": 167, "value": [[21, 238], [10, 731]]}]