[{"instances": "firm", "configurations": 0, "value": [[8629, 386], [51, 1734]]}, {"instances": "firm", "configurations": 1, "value": [[8629, 386], [51, 1734]]}, {"instances": "firm", "configurations": 2, "value": [[8629, 386], [51, 1734]]}, {"instances": "firm", "configurations": 3, "value": [[8629, 386], [51, 1734]]}, {"instances": "firm", "configurations": 4, "value": [[8878, 137], [481, 1304]]}, {"instances": "firm", "configurations": 5, "value": [[8878, 137], [481, 1304]]}, {"instances": "firm", "configurations": 6, "value": [[8003, 1012], [48, 1737]]}, {"instances": "firm", "configurations": 7, "value": [[8003, 1012], [48, 1737]]}, {"instances": "firm", "configurations": 8, "value": [[8605, 410], [3, 1782]]}, {"instances": "firm", "configurations": 9, "value": [[8605, 410], [3, 1782]]}, {"instances": "firm", "configurations": 10, "value": [[8876, 139], [614, 1171]]}, {"instances": "firm", "configurations": 11, "value": [[8876, 139], [614, 1171]]}, {"instances": "firm", "configurations": 12, "value": [[8736, 279], [186, 1599]]}, {"instances": "firm", "configurations": 13, "value": [[8629, 386], [51, 1734]]}, {"instances": "firm", "configurations": 14, "value": [[8736, 279], [186, 1599]]}, {"instances": "firm", "configurations": 15, "value": [[8629, 386], [51, 1734]]}, {"instances": "firm", "configurations": 16, "value": [[8944, 71], [899, 886]]}, {"instances": "firm", "configurations": 17, "value": [[8878, 137], [481, 1304]]}, {"instances": "firm", "configurations": 18, "value": [[8591, 424], [187, 1598]]}, {"instances": "firm", "configurations": 19, "value": [[8586, 429], [171, 1614]]}, {"instances": "firm", "configurations": 20, "value": [[8606, 409], [6, 1779]]}, {"instances": "firm", "configurations": 21, "value": [[8605, 410], [3, 1782]]}, {"instances": "firm", "configurations": 22, "value": [[8944, 71], [1025, 760]]}, {"instances": "firm", "configurations": 23, "value": [[8876, 139], [614, 1171]]}, {"instances": "firm", "configurations": 24, "value": [[8672, 343], [85, 1700]]}, {"instances": "firm", "configurations": 25, "value": [[8673, 342], [78, 1707]]}, {"instances": "firm", "configurations": 26, "value": [[8672, 343], [85, 1700]]}, {"instances": "firm", "configurations": 27, "value": [[8672, 343], [85, 1700]]}, {"instances": "firm", "configurations": 28, "value": [[8858, 157], [480, 1305]]}, {"instances": "firm", "configurations": 29, "value": [[8859, 156], [459, 1326]]}, {"instances": "firm", "configurations": 30, "value": [[8360, 655], [93, 1692]]}, {"instances": "firm", "configurations": 31, "value": [[8481, 534], [95, 1690]]}, {"instances": "firm", "configurations": 32, "value": [[8606, 409], [2, 1783]]}, {"instances": "firm", "configurations": 33, "value": [[8606, 409], [2, 1783]]}, {"instances": "firm", "configurations": 34, "value": [[8858, 157], [558, 1227]]}, {"instances": "firm", "configurations": 35, "value": [[8859, 156], [542, 1243]]}, {"instances": "firm", "configurations": 36, "value": [[8713, 302], [181, 1604]]}, {"instances": "firm", "configurations": 37, "value": [[8673, 342], [81, 1704]]}, {"instances": "firm", "configurations": 38, "value": [[8713, 302], [181, 1604]]}, {"instances": "firm", "configurations": 39, "value": [[8673, 342], [81, 1704]]}, {"instances": "firm", "configurations": 40, "value": [[8921, 94], [767, 1018]]}, {"instances": "firm", "configurations": 41, "value": [[8850, 165], [433, 1352]]}, {"instances": "firm", "configurations": 42, "value": [[8608, 407], [193, 1592]]}, {"instances": "firm", "configurations": 43, "value": [[8604, 411], [158, 1627]]}, {"instances": "firm", "configurations": 44, "value": [[8606, 409], [2, 1783]]}, {"instances": "firm", "configurations": 45, "value": [[8606, 409], [2, 1783]]}, {"instances": "firm", "configurations": 46, "value": [[8921, 94], [828, 957]]}, {"instances": "firm", "configurations": 47, "value": [[8850, 165], [497, 1288]]}, {"instances": "firm", "configurations": 48, "value": [[8661, 354], [60, 1725]]}, {"instances": "firm", "configurations": 49, "value": [[8661, 354], [52, 1733]]}, {"instances": "firm", "configurations": 50, "value": [[8661, 354], [60, 1725]]}, {"instances": "firm", "configurations": 51, "value": [[8661, 354], [60, 1725]]}, {"instances": "firm", "configurations": 52, "value": [[8884, 131], [603, 1182]]}, {"instances": "firm", "configurations": 53, "value": [[8884, 131], [543, 1242]]}, {"instances": "firm", "configurations": 54, "value": [[8480, 535], [64, 1721]]}, {"instances": "firm", "configurations": 55, "value": [[8553, 462], [82, 1703]]}, {"instances": "firm", "configurations": 56, "value": [[8606, 409], [2, 1783]]}, {"instances": "firm", "configurations": 57, "value": [[8606, 409], [2, 1783]]}, {"instances": "firm", "configurations": 58, "value": [[8884, 131], [633, 1152]]}, {"instances": "firm", "configurations": 59, "value": [[8884, 131], [567, 1218]]}, {"instances": "firm", "configurations": 60, "value": [[8682, 333], [92, 1693]]}, {"instances": "firm", "configurations": 61, "value": [[8660, 355], [52, 1733]]}, {"instances": "firm", "configurations": 62, "value": [[8682, 333], [92, 1693]]}, {"instances": "firm", "configurations": 63, "value": [[8660, 355], [52, 1733]]}, {"instances": "firm", "configurations": 64, "value": [[8937, 78], [945, 840]]}, {"instances": "firm", "configurations": 65, "value": [[8881, 134], [563, 1222]]}, {"instances": "firm", "configurations": 66, "value": [[8595, 420], [98, 1687]]}, {"instances": "firm", "configurations": 67, "value": [[8599, 416], [79, 1706]]}, {"instances": "firm", "configurations": 68, "value": [[8606, 409], [2, 1783]]}, {"instances": "firm", "configurations": 69, "value": [[8606, 409], [2, 1783]]}, {"instances": "firm", "configurations": 70, "value": [[8937, 78], [962, 823]]}, {"instances": "firm", "configurations": 71, "value": [[8881, 134], [578, 1207]]}, {"instances": "firm", "configurations": 72, "value": [[8643, 372], [32, 1753]]}, {"instances": "firm", "configurations": 73, "value": [[8643, 372], [31, 1754]]}, {"instances": "firm", "configurations": 74, "value": [[8643, 372], [32, 1753]]}, {"instances": "firm", "configurations": 75, "value": [[8643, 372], [32, 1753]]}, {"instances": "firm", "configurations": 76, "value": [[8925, 90], [890, 895]]}, {"instances": "firm", "configurations": 77, "value": [[8924, 91], [710, 1075]]}, {"instances": "firm", "configurations": 78, "value": [[8507, 508], [36, 1749]]}, {"instances": "firm", "configurations": 79, "value": [[8565, 450], [55, 1730]]}, {"instances": "firm", "configurations": 80, "value": [[8606, 409], [2, 1783]]}, {"instances": "firm", "configurations": 81, "value": [[8606, 409], [2, 1783]]}, {"instances": "firm", "configurations": 82, "value": [[8925, 90], [907, 878]]}, {"instances": "firm", "configurations": 83, "value": [[8925, 90], [722, 1063]]}, {"instances": "firm", "configurations": 84, "value": [[8660, 355], [46, 1739]]}, {"instances": "firm", "configurations": 85, "value": [[8648, 367], [30, 1755]]}, {"instances": "firm", "configurations": 86, "value": [[8660, 355], [46, 1739]]}, {"instances": "firm", "configurations": 87, "value": [[8648, 367], [30, 1755]]}, {"instances": "firm", "configurations": 88, "value": [[8961, 54], [1168, 617]]}, {"instances": "firm", "configurations": 89, "value": [[8919, 96], [780, 1005]]}, {"instances": "firm", "configurations": 90, "value": [[8582, 433], [52, 1733]]}, {"instances": "firm", "configurations": 91, "value": [[8579, 436], [45, 1740]]}, {"instances": "firm", "configurations": 92, "value": [[8606, 409], [2, 1783]]}, {"instances": "firm", "configurations": 93, "value": [[8606, 409], [2, 1783]]}, {"instances": "firm", "configurations": 94, "value": [[8961, 54], [1183, 602]]}, {"instances": "firm", "configurations": 95, "value": [[8919, 96], [794, 991]]}, {"instances": "firm", "configurations": 96, "value": [[8639, 376], [14, 1771]]}, {"instances": "firm", "configurations": 97, "value": [[8639, 376], [21, 1764]]}, {"instances": "firm", "configurations": 98, "value": [[8639, 376], [14, 1771]]}, {"instances": "firm", "configurations": 99, "value": [[8639, 376], [14, 1771]]}, {"instances": "firm", "configurations": 100, "value": [[8953, 62], [1122, 663]]}, {"instances": "firm", "configurations": 101, "value": [[8949, 66], [879, 906]]}, {"instances": "firm", "configurations": 102, "value": [[8539, 476], [22, 1763]]}, {"instances": "firm", "configurations": 103, "value": [[8580, 435], [36, 1749]]}, {"instances": "firm", "configurations": 104, "value": [[8606, 409], [2, 1783]]}, {"instances": "firm", "configurations": 105, "value": [[8606, 409], [2, 1783]]}, {"instances": "firm", "configurations": 106, "value": [[8953, 62], [1136, 649]]}, {"instances": "firm", "configurations": 107, "value": [[8953, 62], [891, 894]]}, {"instances": "firm", "configurations": 108, "value": [[8649, 366], [27, 1758]]}, {"instances": "firm", "configurations": 109, "value": [[8641, 374], [15, 1770]]}, {"instances": "firm", "configurations": 110, "value": [[8649, 366], [27, 1758]]}, {"instances": "firm", "configurations": 111, "value": [[8641, 374], [16, 1769]]}, {"instances": "firm", "configurations": 112, "value": [[8968, 47], [1347, 438]]}, {"instances": "firm", "configurations": 113, "value": [[8949, 66], [967, 818]]}, {"instances": "firm", "configurations": 114, "value": [[8586, 429], [37, 1748]]}, {"instances": "firm", "configurations": 115, "value": [[8587, 428], [30, 1755]]}, {"instances": "firm", "configurations": 116, "value": [[8606, 409], [2, 1783]]}, {"instances": "firm", "configurations": 117, "value": [[8606, 409], [2, 1783]]}, {"instances": "firm", "configurations": 118, "value": [[8968, 47], [1362, 423]]}, {"instances": "firm", "configurations": 119, "value": [[8949, 66], [982, 803]]}, {"instances": "firm", "configurations": 120, "value": [[8685, 330], [59, 1726]]}, {"instances": "firm", "configurations": 121, "value": [[8685, 330], [53, 1732]]}, {"instances": "firm", "configurations": 122, "value": [[8685, 330], [59, 1726]]}, {"instances": "firm", "configurations": 123, "value": [[8685, 330], [57, 1728]]}, {"instances": "firm", "configurations": 124, "value": [[8951, 64], [1294, 491]]}, {"instances": "firm", "configurations": 125, "value": [[8943, 72], [1031, 754]]}, {"instances": "firm", "configurations": 126, "value": [[8631, 384], [67, 1718]]}, {"instances": "firm", "configurations": 127, "value": [[8652, 363], [66, 1719]]}, {"instances": "firm", "configurations": 128, "value": [[8606, 409], [2, 1783]]}, {"instances": "firm", "configurations": 129, "value": [[8606, 409], [2, 1783]]}, {"instances": "firm", "configurations": 130, "value": [[8951, 64], [1304, 481]]}, {"instances": "firm", "configurations": 131, "value": [[8950, 65], [1053, 732]]}, {"instances": "firm", "configurations": 132, "value": [[8740, 275], [145, 1640]]}, {"instances": "firm", "configurations": 133, "value": [[8720, 295], [102, 1683]]}, {"instances": "firm", "configurations": 134, "value": [[8740, 275], [142, 1643]]}, {"instances": "firm", "configurations": 135, "value": [[8721, 294], [106, 1679]]}, {"instances": "firm", "configurations": 136, "value": [[8924, 91], [1130, 655]]}, {"instances": "firm", "configurations": 137, "value": [[8898, 117], [810, 975]]}, {"instances": "firm", "configurations": 138, "value": [[8720, 295], [162, 1623]]}, {"instances": "firm", "configurations": 139, "value": [[8707, 308], [123, 1662]]}, {"instances": "firm", "configurations": 140, "value": [[8606, 409], [2, 1783]]}, {"instances": "firm", "configurations": 141, "value": [[8606, 409], [2, 1783]]}, {"instances": "firm", "configurations": 142, "value": [[8924, 91], [1134, 651]]}, {"instances": "firm", "configurations": 143, "value": [[8898, 117], [817, 968]]}, {"instances": "firm", "configurations": 144, "value": [[8716, 299], [132, 1653]]}, {"instances": "firm", "configurations": 145, "value": [[8725, 290], [122, 1663]]}, {"instances": "firm", "configurations": 146, "value": [[8716, 299], [131, 1654]]}, {"instances": "firm", "configurations": 147, "value": [[8716, 299], [128, 1657]]}, {"instances": "firm", "configurations": 148, "value": [[8892, 123], [783, 1002]]}, {"instances": "firm", "configurations": 149, "value": [[8887, 128], [623, 1162]]}, {"instances": "firm", "configurations": 150, "value": [[8701, 314], [164, 1621]]}, {"instances": "firm", "configurations": 151, "value": [[8719, 296], [160, 1625]]}, {"instances": "firm", "configurations": 152, "value": [[8606, 409], [2, 1783]]}, {"instances": "firm", "configurations": 153, "value": [[8606, 409], [2, 1783]]}, {"instances": "firm", "configurations": 154, "value": [[8891, 124], [787, 998]]}, {"instances": "firm", "configurations": 155, "value": [[8889, 126], [626, 1159]]}, {"instances": "firm", "configurations": 156, "value": [[8703, 312], [111, 1674]]}, {"instances": "firm", "configurations": 157, "value": [[8700, 315], [99, 1686]]}, {"instances": "firm", "configurations": 158, "value": [[8703, 312], [111, 1674]]}, {"instances": "firm", "configurations": 159, "value": [[8698, 317], [95, 1690]]}, {"instances": "firm", "configurations": 160, "value": [[8923, 92], [853, 932]]}, {"instances": "firm", "configurations": 161, "value": [[8899, 116], [601, 1184]]}, {"instances": "firm", "configurations": 162, "value": [[8697, 318], [166, 1619]]}, {"instances": "firm", "configurations": 163, "value": [[8701, 314], [151, 1634]]}, {"instances": "firm", "configurations": 164, "value": [[8606, 409], [2, 1783]]}, {"instances": "firm", "configurations": 165, "value": [[8606, 409], [2, 1783]]}, {"instances": "firm", "configurations": 166, "value": [[8923, 92], [854, 931]]}, {"instances": "firm", "configurations": 167, "value": [[8902, 113], [602, 1183]]}]