[{"instances": "statlog_is", "configurations": 0, "value": [[329, 0, 0, 0, 1, 0, 0], [0, 330, 0, 0, 0, 0, 0], [0, 0, 313, 0, 17, 0, 0], [3, 0, 2, 310, 10, 5, 0], [2, 0, 17, 9, 302, 0, 0], [0, 0, 0, 1, 0, 329, 0], [0, 0, 2, 0, 0, 0, 328]]}, {"instances": "statlog_is", "configurations": 1, "value": [[329, 0, 0, 0, 1, 0, 0], [0, 330, 0, 0, 0, 0, 0], [0, 0, 313, 0, 17, 0, 0], [3, 0, 2, 310, 10, 5, 0], [2, 0, 17, 9, 302, 0, 0], [0, 0, 0, 1, 0, 329, 0], [0, 0, 2, 0, 0, 0, 328]]}, {"instances": "statlog_is", "configurations": 2, "value": [[327, 0, 0, 0, 3, 0, 0], [0, 329, 0, 1, 0, 0, 0], [0, 0, 318, 0, 11, 1, 0], [4, 0, 3, 299, 14, 10, 0], [1, 0, 21, 7, 301, 0, 0], [0, 0, 0, 0, 0, 330, 0], [0, 0, 0, 1, 0, 2, 327]]}, {"instances": "statlog_is", "configurations": 3, "value": [[327, 0, 0, 0, 3, 0, 0], [0, 329, 0, 1, 0, 0, 0], [0, 0, 318, 0, 11, 1, 0], [4, 0, 3, 299, 14, 10, 0], [1, 0, 21, 7, 301, 0, 0], [0, 0, 0, 0, 0, 330, 0], [0, 0, 0, 1, 0, 2, 327]]}, {"instances": "statlog_is", "configurations": 4, "value": [[329, 0, 0, 0, 1, 0, 0], [0, 330, 0, 0, 0, 0, 0], [0, 0, 315, 0, 15, 0, 0], [3, 0, 4, 307, 8, 7, 1], [2, 0, 18, 8, 302, 0, 0], [0, 0, 0, 1, 0, 329, 0], [0, 0, 2, 0, 0, 0, 328]]}, {"instances": "statlog_is", "configurations": 5, "value": [[329, 0, 0, 0, 1, 0, 0], [0, 330, 0, 0, 0, 0, 0], [0, 0, 315, 0, 15, 0, 0], [3, 0, 4, 307, 8, 7, 1], [2, 0, 18, 8, 302, 0, 0], [0, 0, 0, 1, 0, 329, 0], [0, 0, 2, 0, 0, 0, 328]]}, {"instances": "statlog_is", "configurations": 6, "value": [[329, 0, 0, 0, 1, 0, 0], [0, 330, 0, 0, 0, 0, 0], [2, 0, 308, 2, 18, 0, 0], [2, 0, 2, 302, 9, 15, 0], [1, 0, 13, 6, 310, 0, 0], [0, 0, 0, 1, 0, 329, 0], [0, 0, 0, 0, 1, 0, 329]]}, {"instances": "statlog_is", "configurations": 7, "value": [[329, 0, 0, 0, 1, 0, 0], [0, 330, 0, 0, 0, 0, 0], [2, 0, 308, 2, 18, 0, 0], [2, 0, 2, 302, 9, 15, 0], [1, 0, 13, 6, 310, 0, 0], [0, 0, 0, 1, 0, 329, 0], [0, 0, 0, 0, 1, 0, 329]]}, {"instances": "statlog_is", "configurations": 8, "value": [[325, 0, 0, 0, 4, 1, 0], [0, 328, 0, 1, 0, 1, 0], [1, 0, 312, 2, 12, 3, 0], [4, 0, 6, 292, 18, 10, 0], [6, 0, 27, 17, 275, 5, 0], [0, 0, 0, 0, 0, 330, 0], [0, 0, 0, 0, 1, 3, 326]]}, {"instances": "statlog_is", "configurations": 9, "value": [[325, 0, 0, 0, 4, 1, 0], [0, 328, 0, 1, 0, 1, 0], [1, 0, 312, 2, 12, 3, 0], [4, 0, 6, 292, 18, 10, 0], [6, 0, 27, 17, 275, 5, 0], [0, 0, 0, 0, 0, 330, 0], [0, 0, 0, 0, 1, 3, 326]]}, {"instances": "statlog_is", "configurations": 10, "value": [[325, 0, 0, 1, 4, 0, 0], [0, 329, 0, 1, 0, 0, 0], [0, 0, 321, 0, 9, 0, 0], [4, 0, 7, 303, 10, 6, 0], [2, 0, 22, 6, 298, 2, 0], [0, 0, 0, 0, 0, 330, 0], [0, 0, 0, 0, 0, 2, 328]]}, {"instances": "statlog_is", "configurations": 11, "value": [[325, 0, 0, 1, 4, 0, 0], [0, 329, 0, 1, 0, 0, 0], [0, 0, 321, 0, 9, 0, 0], [4, 0, 7, 303, 10, 6, 0], [2, 0, 22, 6, 298, 2, 0], [0, 0, 0, 0, 0, 330, 0], [0, 0, 0, 0, 0, 2, 328]]}, {"instances": "statlog_is", "configurations": 12, "value": [[330, 0, 0, 0, 0, 0, 0], [0, 330, 0, 0, 0, 0, 0], [0, 0, 324, 2, 4, 0, 0], [4, 0, 6, 312, 5, 3, 0], [4, 0, 33, 13, 280, 0, 0], [0, 0, 0, 1, 0, 329, 0], [0, 0, 2, 1, 0, 0, 327]]}, {"instances": "statlog_is", "configurations": 13, "value": [[329, 0, 0, 0, 1, 0, 0], [0, 330, 0, 0, 0, 0, 0], [0, 0, 313, 0, 17, 0, 0], [3, 0, 2, 310, 10, 5, 0], [2, 0, 17, 9, 302, 0, 0], [0, 0, 0, 1, 0, 329, 0], [0, 0, 2, 0, 0, 0, 328]]}, {"instances": "statlog_is", "configurations": 14, "value": [[327, 0, 0, 0, 3, 0, 0], [0, 330, 0, 0, 0, 0, 0], [0, 0, 324, 0, 5, 1, 0], [5, 0, 8, 304, 7, 6, 0], [3, 0, 40, 18, 269, 0, 0], [0, 0, 0, 1, 0, 329, 0], [0, 0, 1, 1, 1, 1, 326]]}, {"instances": "statlog_is", "configurations": 15, "value": [[327, 0, 0, 0, 3, 0, 0], [0, 329, 0, 1, 0, 0, 0], [0, 0, 318, 0, 11, 1, 0], [4, 0, 3, 299, 14, 10, 0], [1, 0, 21, 7, 301, 0, 0], [0, 0, 0, 0, 0, 330, 0], [0, 0, 0, 1, 0, 2, 327]]}, {"instances": "statlog_is", "configurations": 16, "value": [[330, 0, 0, 0, 0, 0, 0], [0, 330, 0, 0, 0, 0, 0], [0, 0, 326, 0, 4, 0, 0], [3, 0, 6, 307, 9, 5, 0], [4, 0, 35, 14, 277, 0, 0], [0, 0, 0, 2, 0, 328, 0], [0, 0, 2, 0, 0, 0, 328]]}, {"instances": "statlog_is", "configurations": 17, "value": [[329, 0, 0, 0, 1, 0, 0], [0, 330, 0, 0, 0, 0, 0], [0, 0, 315, 0, 15, 0, 0], [3, 0, 4, 307, 8, 7, 1], [2, 0, 18, 8, 302, 0, 0], [0, 0, 0, 1, 0, 329, 0], [0, 0, 2, 0, 0, 0, 328]]}, {"instances": "statlog_is", "configurations": 18, "value": [[330, 0, 0, 0, 0, 0, 0], [0, 330, 0, 0, 0, 0, 0], [3, 0, 318, 1, 8, 0, 0], [4, 0, 3, 310, 6, 7, 0], [2, 0, 29, 9, 290, 0, 0], [0, 0, 1, 6, 0, 323, 0], [0, 0, 1, 1, 0, 0, 328]]}, {"instances": "statlog_is", "configurations": 19, "value": [[329, 0, 0, 0, 1, 0, 0], [0, 330, 0, 0, 0, 0, 0], [2, 0, 308, 2, 18, 0, 0], [2, 0, 2, 302, 9, 15, 0], [1, 0, 13, 6, 310, 0, 0], [0, 0, 0, 1, 0, 329, 0], [0, 0, 0, 0, 1, 0, 329]]}, {"instances": "statlog_is", "configurations": 20, "value": [[325, 0, 1, 1, 2, 1, 0], [0, 328, 0, 2, 0, 0, 0], [3, 0, 317, 2, 7, 1, 0], [13, 0, 14, 286, 10, 7, 0], [12, 0, 32, 30, 252, 4, 0], [1, 0, 2, 3, 2, 322, 0], [0, 0, 2, 1, 1, 2, 324]]}, {"instances": "statlog_is", "configurations": 21, "value": [[325, 0, 0, 0, 4, 1, 0], [0, 328, 0, 1, 0, 1, 0], [1, 0, 312, 2, 12, 3, 0], [4, 0, 6, 292, 18, 10, 0], [6, 0, 27, 17, 275, 5, 0], [0, 0, 0, 0, 0, 330, 0], [0, 0, 0, 0, 1, 3, 326]]}, {"instances": "statlog_is", "configurations": 22, "value": [[326, 0, 2, 1, 1, 0, 0], [0, 330, 0, 0, 0, 0, 0], [0, 0, 326, 0, 4, 0, 0], [8, 0, 10, 300, 9, 3, 0], [4, 0, 37, 14, 274, 1, 0], [0, 0, 0, 3, 0, 327, 0], [0, 0, 1, 1, 0, 1, 327]]}, {"instances": "statlog_is", "configurations": 23, "value": [[325, 0, 0, 1, 4, 0, 0], [0, 329, 0, 1, 0, 0, 0], [0, 0, 321, 0, 9, 0, 0], [4, 0, 7, 303, 10, 6, 0], [2, 0, 22, 6, 298, 2, 0], [0, 0, 0, 0, 0, 330, 0], [0, 0, 0, 0, 0, 2, 328]]}, {"instances": "statlog_is", "configurations": 24, "value": [[328, 0, 0, 0, 2, 0, 0], [0, 330, 0, 0, 0, 0, 0], [0, 0, 319, 2, 7, 2, 0], [4, 0, 4, 300, 10, 12, 0], [4, 0, 24, 8, 294, 0, 0], [0, 0, 0, 0, 0, 330, 0], [0, 0, 2, 0, 0, 0, 328]]}, {"instances": "statlog_is", "configurations": 25, "value": [[328, 0, 0, 0, 2, 0, 0], [0, 330, 0, 0, 0, 0, 0], [0, 0, 319, 2, 8, 1, 0], [3, 0, 4, 301, 11, 11, 0], [3, 0, 21, 9, 297, 0, 0], [0, 0, 0, 0, 0, 330, 0], [0, 0, 2, 0, 0, 0, 328]]}, {"instances": "statlog_is", "configurations": 26, "value": [[327, 0, 0, 0, 3, 0, 0], [0, 330, 0, 0, 0, 0, 0], [0, 0, 313, 4, 9, 4, 0], [7, 0, 8, 287, 12, 16, 0], [6, 0, 26, 10, 286, 2, 0], [0, 0, 0, 0, 0, 330, 0], [0, 0, 0, 0, 1, 2, 327]]}, {"instances": "statlog_is", "configurations": 27, "value": [[327, 0, 0, 0, 3, 0, 0], [0, 330, 0, 0, 0, 0, 0], [0, 0, 315, 3, 10, 2, 0], [5, 0, 5, 293, 12, 15, 0], [2, 0, 25, 10, 291, 2, 0], [0, 0, 0, 0, 0, 330, 0], [0, 0, 0, 0, 1, 2, 327]]}, {"instances": "statlog_is", "configurations": 28, "value": [[328, 0, 0, 0, 2, 0, 0], [0, 330, 0, 0, 0, 0, 0], [0, 0, 322, 0, 8, 0, 0], [3, 0, 5, 299, 9, 14, 0], [6, 0, 23, 9, 292, 0, 0], [0, 0, 0, 0, 0, 330, 0], [0, 0, 1, 0, 0, 1, 328]]}, {"instances": "statlog_is", "configurations": 29, "value": [[328, 0, 0, 0, 2, 0, 0], [0, 330, 0, 0, 0, 0, 0], [0, 0, 321, 0, 9, 0, 0], [3, 0, 5, 300, 9, 12, 1], [2, 0, 21, 10, 297, 0, 0], [0, 0, 0, 0, 0, 330, 0], [0, 0, 1, 0, 0, 1, 328]]}, {"instances": "statlog_is", "configurations": 30, "value": [[330, 0, 0, 0, 0, 0, 0], [0, 330, 0, 0, 0, 0, 0], [2, 0, 315, 0, 13, 0, 0], [4, 0, 3, 287, 9, 27, 0], [2, 0, 18, 6, 304, 0, 0], [0, 0, 0, 2, 0, 328, 0], [0, 0, 1, 1, 0, 0, 328]]}, {"instances": "statlog_is", "configurations": 31, "value": [[330, 0, 0, 0, 0, 0, 0], [0, 330, 0, 0, 0, 0, 0], [1, 0, 315, 1, 13, 0, 0], [4, 0, 2, 289, 9, 26, 0], [1, 0, 12, 6, 311, 0, 0], [0, 0, 0, 2, 0, 328, 0], [0, 0, 1, 0, 1, 0, 328]]}, {"instances": "statlog_is", "configurations": 32, "value": [[323, 0, 2, 0, 4, 1, 0], [0, 329, 0, 1, 0, 0, 0], [2, 0, 305, 4, 14, 5, 0], [12, 0, 8, 275, 21, 14, 0], [10, 0, 25, 13, 277, 5, 0], [2, 0, 1, 2, 0, 325, 0], [0, 0, 1, 1, 1, 3, 324]]}, {"instances": "statlog_is", "configurations": 33, "value": [[325, 0, 0, 0, 4, 1, 0], [0, 328, 0, 1, 0, 1, 0], [1, 0, 311, 2, 13, 3, 0], [9, 0, 5, 283, 21, 12, 0], [7, 0, 26, 14, 278, 5, 0], [0, 0, 0, 1, 0, 329, 0], [0, 0, 0, 0, 1, 3, 326]]}, {"instances": "statlog_is", "configurations": 34, "value": [[324, 0, 0, 1, 5, 0, 0], [0, 330, 0, 0, 0, 0, 0], [0, 0, 322, 1, 7, 0, 0], [8, 0, 10, 285, 16, 11, 0], [5, 0, 27, 12, 283, 3, 0], [0, 0, 0, 1, 0, 329, 0], [0, 0, 0, 0, 0, 2, 328]]}, {"instances": "statlog_is", "configurations": 35, "value": [[325, 0, 0, 1, 4, 0, 0], [0, 330, 0, 0, 0, 0, 0], [0, 0, 322, 0, 8, 0, 0], [5, 0, 8, 294, 12, 11, 0], [3, 0, 22, 8, 295, 2, 0], [0, 0, 0, 0, 0, 330, 0], [0, 0, 0, 0, 0, 2, 328]]}, {"instances": "statlog_is", "configurations": 36, "value": [[329, 0, 0, 0, 1, 0, 0], [0, 330, 0, 0, 0, 0, 0], [0, 0, 320, 2, 7, 1, 0], [5, 0, 4, 308, 4, 9, 0], [3, 0, 32, 11, 284, 0, 0], [0, 0, 0, 0, 0, 330, 0], [0, 0, 1, 1, 1, 0, 327]]}, {"instances": "statlog_is", "configurations": 37, "value": [[329, 0, 0, 0, 1, 0, 0], [0, 330, 0, 0, 0, 0, 0], [0, 0, 317, 1, 12, 0, 0], [4, 0, 4, 305, 8, 9, 0], [3, 0, 22, 7, 298, 0, 0], [0, 0, 0, 0, 0, 330, 0], [0, 0, 1, 0, 1, 0, 328]]}, {"instances": "statlog_is", "configurations": 38, "value": [[325, 0, 0, 2, 3, 0, 0], [0, 330, 0, 0, 0, 0, 0], [0, 0, 317, 1, 8, 4, 0], [9, 0, 7, 292, 9, 13, 0], [9, 0, 32, 13, 272, 4, 0], [0, 0, 0, 0, 0, 330, 0], [0, 0, 0, 1, 1, 2, 326]]}, {"instances": "statlog_is", "configurations": 39, "value": [[326, 0, 0, 0, 4, 0, 0], [0, 330, 0, 0, 0, 0, 0], [0, 0, 315, 1, 12, 2, 0], [5, 0, 4, 293, 13, 15, 0], [5, 0, 24, 6, 291, 4, 0], [0, 0, 0, 0, 0, 330, 0], [0, 0, 0, 1, 0, 2, 327]]}, {"instances": "statlog_is", "configurations": 40, "value": [[328, 0, 0, 0, 2, 0, 0], [0, 330, 0, 0, 0, 0, 0], [0, 2, 320, 1, 7, 0, 0], [3, 0, 6, 304, 7, 10, 0], [3, 0, 35, 11, 281, 0, 0], [0, 0, 0, 0, 0, 330, 0], [0, 0, 1, 0, 0, 1, 328]]}, {"instances": "statlog_is", "configurations": 41, "value": [[327, 0, 0, 0, 3, 0, 0], [0, 330, 0, 0, 0, 0, 0], [0, 0, 318, 0, 12, 0, 0], [3, 0, 4, 304, 8, 11, 0], [2, 0, 22, 9, 297, 0, 0], [0, 0, 0, 0, 0, 330, 0], [0, 0, 1, 0, 0, 1, 328]]}, {"instances": "statlog_is", "configurations": 42, "value": [[330, 0, 0, 0, 0, 0, 0], [0, 330, 0, 0, 0, 0, 0], [1, 0, 319, 1, 9, 0, 0], [4, 0, 3, 296, 8, 19, 0], [2, 0, 23, 8, 297, 0, 0], [0, 0, 1, 4, 0, 325, 0], [0, 0, 1, 0, 0, 0, 329]]}, {"instances": "statlog_is", "configurations": 43, "value": [[330, 0, 0, 0, 0, 0, 0], [0, 330, 0, 0, 0, 0, 0], [1, 0, 313, 2, 14, 0, 0], [4, 0, 2, 293, 9, 22, 0], [2, 0, 15, 5, 308, 0, 0], [0, 0, 0, 1, 0, 329, 0], [0, 0, 1, 0, 0, 0, 329]]}, {"instances": "statlog_is", "configurations": 44, "value": [[323, 0, 3, 0, 3, 1, 0], [0, 328, 0, 1, 0, 1, 0], [3, 0, 308, 4, 10, 5, 0], [13, 1, 8, 284, 11, 13, 0], [11, 0, 33, 25, 257, 4, 0], [1, 0, 1, 3, 0, 325, 0], [0, 0, 1, 1, 2, 2, 324]]}, {"instances": "statlog_is", "configurations": 45, "value": [[325, 0, 2, 0, 2, 1, 0], [0, 328, 0, 1, 0, 1, 0], [1, 0, 314, 1, 11, 3, 0], [8, 0, 8, 285, 17, 12, 0], [7, 0, 26, 15, 276, 6, 0], [0, 0, 0, 1, 0, 329, 0], [0, 0, 0, 0, 2, 3, 325]]}, {"instances": "statlog_is", "configurations": 46, "value": [[324, 0, 1, 2, 3, 0, 0], [0, 330, 0, 0, 0, 0, 0], [0, 0, 325, 0, 5, 0, 0], [9, 1, 10, 289, 12, 9, 0], [8, 0, 33, 15, 269, 5, 0], [0, 0, 0, 1, 0, 329, 0], [0, 0, 0, 0, 1, 2, 327]]}, {"instances": "statlog_is", "configurations": 47, "value": [[325, 0, 0, 1, 4, 0, 0], [0, 330, 0, 0, 0, 0, 0], [0, 0, 322, 0, 8, 0, 0], [5, 0, 8, 297, 10, 10, 0], [3, 0, 25, 7, 291, 4, 0], [0, 0, 0, 0, 0, 330, 0], [0, 0, 0, 0, 0, 2, 328]]}, {"instances": "statlog_is", "configurations": 48, "value": [[329, 0, 0, 0, 1, 0, 0], [0, 330, 0, 0, 0, 0, 0], [0, 0, 316, 2, 9, 3, 0], [5, 0, 3, 290, 20, 12, 0], [6, 0, 29, 6, 289, 0, 0], [0, 0, 0, 0, 0, 330, 0], [0, 0, 2, 0, 0, 0, 328]]}, {"instances": "statlog_is", "configurations": 49, "value": [[328, 0, 0, 0, 2, 0, 0], [0, 330, 0, 0, 0, 0, 0], [0, 0, 318, 2, 9, 1, 0], [4, 0, 3, 295, 17, 11, 0], [3, 0, 30, 7, 290, 0, 0], [0, 0, 0, 0, 0, 330, 0], [0, 0, 2, 0, 0, 0, 328]]}, {"instances": "statlog_is", "configurations": 50, "value": [[325, 0, 0, 2, 3, 0, 0], [0, 330, 0, 0, 0, 0, 0], [1, 0, 314, 2, 9, 4, 0], [10, 0, 7, 276, 17, 20, 0], [10, 0, 28, 8, 279, 5, 0], [0, 0, 0, 0, 0, 330, 0], [0, 0, 0, 1, 0, 2, 327]]}, {"instances": "statlog_is", "configurations": 51, "value": [[326, 0, 0, 0, 4, 0, 0], [0, 330, 0, 0, 0, 0, 0], [0, 0, 315, 2, 12, 1, 0], [8, 0, 7, 282, 15, 18, 0], [2, 0, 27, 8, 288, 5, 0], [0, 0, 0, 0, 0, 330, 0], [0, 0, 0, 1, 0, 2, 327]]}, {"instances": "statlog_is", "configurations": 52, "value": [[328, 0, 0, 0, 2, 0, 0], [0, 330, 0, 0, 0, 0, 0], [0, 2, 319, 0, 8, 1, 0], [4, 0, 6, 289, 14, 17, 0], [4, 0, 29, 6, 291, 0, 0], [0, 0, 0, 0, 0, 330, 0], [0, 0, 1, 0, 0, 1, 328]]}, {"instances": "statlog_is", "configurations": 53, "value": [[327, 0, 0, 0, 3, 0, 0], [0, 330, 0, 0, 0, 0, 0], [0, 0, 322, 0, 8, 0, 0], [3, 0, 5, 296, 11, 15, 0], [3, 0, 30, 5, 292, 0, 0], [0, 0, 0, 0, 0, 330, 0], [0, 0, 1, 0, 0, 1, 328]]}, {"instances": "statlog_is", "configurations": 54, "value": [[330, 0, 0, 0, 0, 0, 0], [0, 330, 0, 0, 0, 0, 0], [3, 0, 311, 1, 15, 0, 0], [6, 0, 2, 282, 13, 26, 1], [2, 0, 19, 4, 305, 0, 0], [0, 0, 0, 1, 0, 329, 0], [0, 0, 1, 1, 0, 0, 328]]}, {"instances": "statlog_is", "configurations": 55, "value": [[330, 0, 0, 0, 0, 0, 0], [0, 330, 0, 0, 0, 0, 0], [1, 0, 313, 1, 15, 0, 0], [4, 0, 2, 286, 12, 25, 1], [1, 0, 15, 4, 310, 0, 0], [0, 0, 0, 1, 0, 329, 0], [0, 0, 1, 1, 0, 0, 328]]}, {"instances": "statlog_is", "configurations": 56, "value": [[322, 0, 3, 0, 4, 1, 0], [0, 328, 0, 1, 0, 1, 0], [5, 0, 297, 6, 17, 5, 0], [13, 1, 9, 273, 17, 17, 0], [12, 0, 31, 20, 261, 6, 0], [0, 0, 1, 2, 1, 326, 0], [0, 0, 2, 0, 1, 3, 324]]}, {"instances": "statlog_is", "configurations": 57, "value": [[325, 0, 2, 0, 2, 1, 0], [0, 328, 0, 1, 0, 1, 0], [1, 0, 309, 1, 13, 6, 0], [9, 1, 7, 284, 16, 13, 0], [8, 0, 25, 16, 275, 6, 0], [0, 0, 0, 0, 0, 330, 0], [0, 0, 1, 0, 1, 3, 325]]}, {"instances": "statlog_is", "configurations": 58, "value": [[323, 0, 1, 2, 4, 0, 0], [0, 330, 0, 0, 0, 0, 0], [0, 0, 318, 0, 11, 1, 0], [8, 1, 8, 278, 23, 12, 0], [7, 0, 30, 9, 279, 5, 0], [0, 0, 0, 0, 0, 330, 0], [0, 0, 0, 0, 1, 2, 327]]}, {"instances": "statlog_is", "configurations": 59, "value": [[325, 0, 0, 1, 4, 0, 0], [0, 330, 0, 0, 0, 0, 0], [0, 0, 322, 0, 8, 0, 0], [5, 1, 8, 294, 10, 12, 0], [3, 0, 24, 6, 293, 4, 0], [0, 0, 0, 0, 0, 330, 0], [0, 0, 0, 0, 0, 2, 328]]}, {"instances": "statlog_is", "configurations": 60, "value": [[328, 0, 0, 0, 2, 0, 0], [0, 330, 0, 0, 0, 0, 0], [1, 0, 318, 2, 6, 3, 0], [5, 0, 4, 298, 14, 9, 0], [7, 0, 35, 9, 279, 0, 0], [0, 0, 0, 0, 0, 330, 0], [0, 0, 2, 0, 0, 0, 328]]}, {"instances": "statlog_is", "configurations": 61, "value": [[329, 0, 0, 0, 1, 0, 0], [0, 330, 0, 0, 0, 0, 0], [0, 0, 318, 3, 8, 1, 0], [4, 0, 3, 298, 15, 10, 0], [5, 0, 26, 5, 294, 0, 0], [0, 0, 0, 0, 0, 330, 0], [0, 0, 2, 0, 0, 0, 328]]}, {"instances": "statlog_is", "configurations": 62, "value": [[325, 0, 0, 0, 5, 0, 0], [0, 330, 0, 0, 0, 0, 0], [0, 0, 318, 3, 6, 3, 0], [11, 0, 9, 279, 15, 16, 0], [10, 0, 33, 10, 273, 4, 0], [0, 0, 0, 0, 0, 330, 0], [0, 0, 0, 1, 0, 2, 327]]}, {"instances": "statlog_is", "configurations": 63, "value": [[326, 0, 0, 0, 4, 0, 0], [0, 330, 0, 0, 0, 0, 0], [0, 0, 316, 3, 10, 1, 0], [8, 0, 5, 289, 13, 15, 0], [4, 0, 27, 8, 287, 4, 0], [0, 0, 0, 0, 0, 330, 0], [0, 0, 0, 1, 0, 2, 327]]}, {"instances": "statlog_is", "configurations": 64, "value": [[326, 0, 0, 0, 4, 0, 0], [0, 330, 0, 0, 0, 0, 0], [0, 2, 322, 0, 5, 1, 0], [4, 0, 7, 292, 13, 14, 0], [8, 0, 35, 11, 276, 0, 0], [0, 0, 0, 0, 0, 330, 0], [0, 0, 1, 0, 0, 1, 328]]}, {"instances": "statlog_is", "configurations": 65, "value": [[327, 0, 0, 0, 3, 0, 0], [0, 330, 0, 0, 0, 0, 0], [0, 0, 322, 0, 8, 0, 0], [3, 0, 4, 297, 12, 14, 0], [4, 0, 24, 7, 295, 0, 0], [0, 0, 0, 0, 0, 330, 0], [0, 0, 1, 0, 0, 1, 328]]}, {"instances": "statlog_is", "configurations": 66, "value": [[330, 0, 0, 0, 0, 0, 0], [0, 330, 0, 0, 0, 0, 0], [2, 0, 316, 0, 11, 1, 0], [6, 0, 2, 288, 13, 21, 0], [3, 0, 23, 6, 298, 0, 0], [0, 0, 0, 3, 0, 327, 0], [0, 0, 1, 1, 0, 0, 328]]}, {"instances": "statlog_is", "configurations": 67, "value": [[330, 0, 0, 0, 0, 0, 0], [0, 330, 0, 0, 0, 0, 0], [1, 0, 314, 0, 14, 1, 0], [6, 0, 1, 287, 13, 23, 0], [2, 0, 14, 4, 310, 0, 0], [0, 0, 0, 2, 0, 328, 0], [0, 0, 1, 1, 0, 0, 328]]}, {"instances": "statlog_is", "configurations": 68, "value": [[323, 0, 2, 0, 4, 1, 0], [0, 328, 0, 1, 0, 1, 0], [3, 0, 302, 6, 13, 6, 0], [17, 1, 8, 271, 15, 18, 0], [12, 0, 38, 24, 250, 6, 0], [0, 0, 1, 2, 1, 326, 0], [1, 0, 0, 0, 3, 3, 323]]}, {"instances": "statlog_is", "configurations": 69, "value": [[325, 0, 2, 0, 2, 1, 0], [0, 328, 0, 1, 0, 1, 0], [1, 0, 309, 3, 11, 6, 0], [11, 1, 8, 281, 14, 15, 0], [6, 0, 27, 16, 274, 7, 0], [0, 0, 0, 0, 0, 330, 0], [0, 0, 0, 0, 3, 3, 324]]}, {"instances": "statlog_is", "configurations": 70, "value": [[323, 0, 1, 1, 5, 0, 0], [0, 330, 0, 0, 0, 0, 0], [0, 0, 323, 1, 6, 0, 0], [10, 1, 11, 275, 23, 10, 0], [8, 0, 36, 13, 268, 5, 0], [0, 0, 0, 1, 0, 329, 0], [0, 0, 0, 0, 1, 2, 327]]}, {"instances": "statlog_is", "configurations": 71, "value": [[325, 0, 0, 1, 4, 0, 0], [0, 330, 0, 0, 0, 0, 0], [0, 0, 322, 0, 8, 0, 0], [5, 1, 8, 294, 11, 11, 0], [3, 0, 26, 5, 292, 4, 0], [0, 0, 0, 0, 0, 330, 0], [0, 0, 0, 0, 0, 2, 328]]}, {"instances": "statlog_is", "configurations": 72, "value": [[329, 0, 0, 0, 1, 0, 0], [0, 330, 0, 0, 0, 0, 0], [1, 0, 315, 4, 7, 3, 0], [5, 0, 2, 290, 19, 14, 0], [4, 0, 32, 9, 285, 0, 0], [0, 0, 0, 0, 0, 330, 0], [0, 0, 1, 0, 0, 1, 328]]}, {"instances": "statlog_is", "configurations": 73, "value": [[329, 0, 0, 0, 1, 0, 0], [0, 330, 0, 0, 0, 0, 0], [0, 0, 318, 3, 8, 1, 0], [4, 0, 2, 294, 17, 13, 0], [4, 0, 27, 7, 292, 0, 0], [0, 0, 0, 0, 0, 330, 0], [0, 0, 1, 0, 0, 1, 328]]}, {"instances": "statlog_is", "configurations": 74, "value": [[326, 0, 2, 0, 2, 0, 0], [0, 330, 0, 0, 0, 0, 0], [0, 0, 313, 3, 11, 3, 0], [10, 0, 8, 269, 24, 19, 0], [12, 0, 31, 9, 274, 4, 0], [0, 0, 0, 0, 0, 330, 0], [0, 0, 0, 1, 0, 2, 327]]}, {"instances": "statlog_is", "configurations": 75, "value": [[326, 0, 0, 0, 4, 0, 0], [0, 330, 0, 0, 0, 0, 0], [0, 0, 315, 3, 12, 0, 0], [7, 0, 6, 281, 20, 16, 0], [5, 0, 25, 10, 286, 4, 0], [0, 0, 0, 0, 0, 330, 0], [0, 0, 0, 1, 0, 2, 327]]}, {"instances": "statlog_is", "configurations": 76, "value": [[327, 0, 0, 0, 3, 0, 0], [0, 330, 0, 0, 0, 0, 0], [0, 2, 321, 0, 6, 1, 0], [6, 0, 5, 280, 19, 20, 0], [5, 0, 31, 6, 288, 0, 0], [0, 0, 0, 0, 0, 330, 0], [0, 0, 1, 0, 0, 1, 328]]}, {"instances": "statlog_is", "configurations": 77, "value": [[327, 0, 0, 0, 3, 0, 0], [0, 330, 0, 0, 0, 0, 0], [0, 1, 323, 0, 6, 0, 0], [4, 0, 3, 291, 16, 16, 0], [4, 0, 27, 4, 295, 0, 0], [0, 0, 0, 0, 0, 330, 0], [0, 0, 1, 0, 0, 1, 328]]}, {"instances": "statlog_is", "configurations": 78, "value": [[330, 0, 0, 0, 0, 0, 0], [0, 330, 0, 0, 0, 0, 0], [2, 0, 307, 0, 20, 1, 0], [5, 0, 1, 272, 17, 34, 1], [2, 0, 20, 5, 303, 0, 0], [0, 0, 0, 2, 0, 328, 0], [0, 0, 1, 1, 0, 0, 328]]}, {"instances": "statlog_is", "configurations": 79, "value": [[330, 0, 0, 0, 0, 0, 0], [0, 330, 0, 0, 0, 0, 0], [1, 0, 311, 0, 17, 1, 0], [5, 0, 1, 277, 16, 30, 1], [2, 0, 17, 5, 306, 0, 0], [0, 0, 0, 2, 0, 328, 0], [0, 0, 1, 1, 0, 0, 328]]}, {"instances": "statlog_is", "configurations": 80, "value": [[322, 0, 2, 0, 5, 1, 0], [0, 328, 0, 1, 0, 1, 0], [1, 0, 301, 4, 18, 6, 0], [12, 1, 8, 265, 21, 23, 0], [14, 0, 37, 22, 250, 7, 0], [0, 0, 1, 0, 0, 329, 0], [2, 0, 0, 0, 3, 3, 322]]}, {"instances": "statlog_is", "configurations": 81, "value": [[325, 0, 2, 0, 2, 1, 0], [0, 328, 0, 1, 0, 1, 0], [0, 0, 310, 1, 13, 6, 0], [11, 1, 8, 277, 16, 17, 0], [8, 0, 26, 17, 272, 7, 0], [0, 0, 0, 0, 0, 330, 0], [0, 0, 0, 0, 3, 3, 324]]}, {"instances": "statlog_is", "configurations": 82, "value": [[323, 0, 1, 0, 6, 0, 0], [0, 330, 0, 0, 0, 0, 0], [0, 0, 318, 1, 9, 2, 0], [10, 1, 10, 268, 24, 17, 0], [7, 0, 34, 10, 274, 5, 0], [0, 0, 0, 0, 0, 330, 0], [0, 0, 0, 1, 1, 2, 326]]}, {"instances": "statlog_is", "configurations": 83, "value": [[325, 0, 0, 1, 4, 0, 0], [0, 330, 0, 0, 0, 0, 0], [0, 0, 321, 0, 8, 1, 0], [5, 1, 8, 290, 13, 13, 0], [4, 0, 27, 6, 289, 4, 0], [0, 0, 0, 0, 0, 330, 0], [0, 0, 0, 0, 0, 2, 328]]}, {"instances": "statlog_is", "configurations": 84, "value": [[329, 0, 0, 0, 1, 0, 0], [0, 330, 0, 0, 0, 0, 0], [0, 0, 315, 5, 7, 3, 0], [4, 0, 4, 290, 20, 12, 0], [4, 0, 37, 6, 283, 0, 0], [0, 0, 0, 0, 0, 330, 0], [0, 0, 1, 1, 0, 1, 327]]}, {"instances": "statlog_is", "configurations": 85, "value": [[329, 0, 0, 0, 1, 0, 0], [0, 330, 0, 0, 0, 0, 0], [0, 0, 317, 4, 8, 1, 0], [4, 0, 2, 294, 17, 13, 0], [3, 0, 27, 3, 297, 0, 0], [0, 0, 0, 0, 0, 330, 0], [0, 0, 1, 0, 0, 1, 328]]}, {"instances": "statlog_is", "configurations": 86, "value": [[324, 0, 3, 0, 3, 0, 0], [0, 330, 0, 0, 0, 0, 0], [0, 0, 314, 4, 9, 3, 0], [10, 0, 8, 271, 23, 18, 0], [8, 0, 39, 11, 268, 4, 0], [0, 0, 0, 0, 0, 330, 0], [0, 0, 0, 1, 0, 2, 327]]}, {"instances": "statlog_is", "configurations": 87, "value": [[325, 0, 1, 0, 4, 0, 0], [0, 330, 0, 0, 0, 0, 0], [0, 0, 316, 3, 10, 1, 0], [7, 0, 4, 287, 18, 14, 0], [4, 0, 29, 8, 285, 4, 0], [0, 0, 0, 0, 0, 330, 0], [0, 0, 0, 1, 0, 2, 327]]}, {"instances": "statlog_is", "configurations": 88, "value": [[327, 0, 1, 0, 2, 0, 0], [0, 330, 0, 0, 0, 0, 0], [1, 2, 320, 0, 6, 1, 0], [6, 0, 4, 286, 17, 17, 0], [5, 0, 39, 8, 278, 0, 0], [0, 0, 0, 0, 0, 330, 0], [0, 0, 1, 0, 0, 1, 328]]}, {"instances": "statlog_is", "configurations": 89, "value": [[327, 0, 0, 0, 3, 0, 0], [0, 330, 0, 0, 0, 0, 0], [0, 1, 322, 0, 7, 0, 0], [5, 0, 3, 291, 15, 16, 0], [4, 0, 30, 2, 294, 0, 0], [0, 0, 0, 0, 0, 330, 0], [0, 0, 1, 0, 0, 1, 328]]}, {"instances": "statlog_is", "configurations": 90, "value": [[327, 0, 0, 0, 3, 0, 0], [0, 330, 0, 0, 0, 0, 0], [3, 0, 311, 0, 15, 1, 0], [4, 0, 2, 275, 17, 31, 1], [2, 0, 23, 8, 297, 0, 0], [0, 0, 0, 5, 0, 325, 0], [0, 0, 1, 1, 0, 0, 328]]}, {"instances": "statlog_is", "configurations": 91, "value": [[329, 0, 0, 0, 1, 0, 0], [0, 330, 0, 0, 0, 0, 0], [1, 0, 313, 0, 15, 1, 0], [5, 0, 1, 278, 16, 29, 1], [2, 0, 17, 6, 305, 0, 0], [0, 0, 0, 2, 0, 328, 0], [0, 0, 1, 1, 0, 0, 328]]}, {"instances": "statlog_is", "configurations": 92, "value": [[322, 0, 2, 0, 5, 1, 0], [0, 328, 0, 1, 0, 1, 0], [1, 0, 299, 4, 19, 7, 0], [19, 1, 7, 262, 20, 21, 0], [14, 0, 37, 30, 243, 6, 0], [0, 0, 0, 1, 0, 329, 0], [2, 0, 0, 0, 3, 3, 322]]}, {"instances": "statlog_is", "configurations": 93, "value": [[325, 0, 2, 0, 2, 1, 0], [0, 328, 0, 1, 0, 1, 0], [0, 0, 309, 1, 14, 6, 0], [11, 1, 7, 278, 16, 17, 0], [11, 0, 27, 18, 268, 6, 0], [0, 0, 0, 0, 0, 330, 0], [0, 0, 0, 0, 3, 3, 324]]}, {"instances": "statlog_is", "configurations": 94, "value": [[323, 0, 1, 1, 5, 0, 0], [0, 330, 0, 0, 0, 0, 0], [0, 0, 320, 1, 7, 2, 0], [9, 1, 10, 271, 24, 15, 0], [6, 0, 42, 12, 265, 5, 0], [0, 0, 0, 0, 0, 330, 0], [0, 0, 0, 0, 0, 2, 328]]}, {"instances": "statlog_is", "configurations": 95, "value": [[325, 0, 0, 1, 4, 0, 0], [0, 330, 0, 0, 0, 0, 0], [0, 0, 322, 0, 8, 0, 0], [5, 1, 8, 289, 13, 14, 0], [4, 0, 25, 8, 288, 5, 0], [0, 0, 0, 0, 0, 330, 0], [0, 0, 0, 0, 0, 2, 328]]}, {"instances": "statlog_is", "configurations": 96, "value": [[329, 0, 0, 0, 1, 0, 0], [0, 330, 0, 0, 0, 0, 0], [0, 0, 312, 4, 10, 4, 0], [4, 0, 1, 284, 24, 17, 0], [5, 0, 32, 5, 288, 0, 0], [0, 0, 0, 0, 0, 330, 0], [0, 0, 1, 1, 0, 1, 327]]}, {"instances": "statlog_is", "configurations": 97, "value": [[329, 0, 0, 0, 1, 0, 0], [0, 330, 0, 0, 0, 0, 0], [0, 0, 318, 3, 7, 2, 0], [5, 0, 1, 291, 20, 13, 0], [4, 0, 27, 2, 297, 0, 0], [0, 0, 0, 0, 0, 330, 0], [0, 0, 1, 0, 0, 1, 328]]}, {"instances": "statlog_is", "configurations": 98, "value": [[324, 0, 3, 0, 3, 0, 0], [0, 330, 0, 0, 0, 0, 0], [1, 0, 307, 4, 15, 3, 0], [8, 0, 8, 269, 23, 22, 0], [11, 0, 35, 9, 271, 4, 0], [0, 0, 0, 0, 0, 330, 0], [0, 0, 0, 1, 0, 2, 327]]}, {"instances": "statlog_is", "configurations": 99, "value": [[325, 0, 3, 0, 2, 0, 0], [0, 330, 0, 0, 0, 0, 0], [0, 0, 313, 4, 12, 1, 0], [7, 0, 5, 282, 18, 18, 0], [4, 0, 28, 8, 286, 4, 0], [0, 0, 0, 0, 0, 330, 0], [0, 0, 0, 1, 0, 2, 327]]}, {"instances": "statlog_is", "configurations": 100, "value": [[327, 0, 0, 0, 3, 0, 0], [0, 330, 0, 0, 0, 0, 0], [1, 2, 317, 0, 10, 0, 0], [7, 0, 3, 275, 20, 25, 0], [5, 0, 37, 6, 282, 0, 0], [0, 0, 0, 0, 0, 330, 0], [0, 0, 1, 0, 0, 1, 328]]}, {"instances": "statlog_is", "configurations": 101, "value": [[327, 0, 0, 0, 3, 0, 0], [0, 330, 0, 0, 0, 0, 0], [0, 2, 321, 0, 7, 0, 0], [6, 0, 4, 283, 17, 20, 0], [4, 0, 33, 4, 289, 0, 0], [0, 0, 0, 0, 0, 330, 0], [0, 0, 1, 0, 0, 1, 328]]}, {"instances": "statlog_is", "configurations": 102, "value": [[328, 0, 0, 0, 2, 0, 0], [0, 330, 0, 0, 0, 0, 0], [3, 0, 304, 1, 20, 2, 0], [3, 0, 1, 269, 17, 39, 1], [2, 0, 22, 6, 300, 0, 0], [0, 0, 0, 3, 0, 327, 0], [0, 0, 1, 1, 0, 0, 328]]}, {"instances": "statlog_is", "configurations": 103, "value": [[329, 0, 0, 0, 1, 0, 0], [0, 330, 0, 0, 0, 0, 0], [1, 0, 310, 1, 16, 2, 0], [3, 0, 1, 273, 17, 35, 1], [2, 0, 19, 6, 303, 0, 0], [0, 0, 0, 3, 0, 327, 0], [0, 0, 1, 1, 0, 0, 328]]}, {"instances": "statlog_is", "configurations": 104, "value": [[322, 0, 3, 0, 4, 1, 0], [0, 328, 0, 0, 0, 2, 0], [1, 0, 299, 4, 19, 7, 0], [20, 1, 9, 255, 19, 26, 0], [12, 0, 32, 25, 253, 8, 0], [0, 0, 1, 0, 0, 329, 0], [3, 0, 0, 0, 3, 3, 321]]}, {"instances": "statlog_is", "configurations": 105, "value": [[325, 0, 2, 0, 2, 1, 0], [0, 328, 0, 0, 0, 2, 0], [0, 0, 309, 2, 13, 6, 0], [12, 1, 6, 276, 16, 19, 0], [8, 0, 26, 21, 267, 8, 0], [0, 0, 0, 0, 0, 330, 0], [0, 0, 0, 0, 3, 3, 324]]}, {"instances": "statlog_is", "configurations": 106, "value": [[323, 0, 3, 0, 4, 0, 0], [0, 330, 0, 0, 0, 0, 0], [0, 0, 316, 1, 11, 2, 0], [10, 1, 10, 265, 22, 22, 0], [7, 0, 43, 10, 265, 5, 0], [0, 0, 0, 0, 0, 330, 0], [0, 0, 0, 1, 0, 2, 327]]}, {"instances": "statlog_is", "configurations": 107, "value": [[325, 0, 0, 1, 4, 0, 0], [0, 330, 0, 0, 0, 0, 0], [0, 0, 322, 0, 7, 1, 0], [5, 1, 7, 289, 12, 16, 0], [4, 0, 27, 6, 288, 5, 0], [0, 0, 0, 0, 0, 330, 0], [0, 0, 0, 0, 0, 2, 328]]}, {"instances": "statlog_is", "configurations": 108, "value": [[327, 0, 0, 0, 3, 0, 0], [0, 330, 0, 0, 0, 0, 0], [0, 0, 313, 6, 7, 4, 0], [4, 0, 1, 288, 24, 13, 0], [4, 0, 40, 8, 278, 0, 0], [0, 0, 0, 0, 0, 330, 0], [0, 0, 1, 0, 0, 1, 328]]}, {"instances": "statlog_is", "configurations": 109, "value": [[328, 0, 0, 0, 2, 0, 0], [0, 330, 0, 0, 0, 0, 0], [0, 0, 317, 3, 8, 2, 0], [5, 0, 1, 291, 20, 13, 0], [3, 0, 29, 2, 296, 0, 0], [0, 0, 0, 0, 0, 330, 0], [0, 0, 1, 0, 0, 1, 328]]}, {"instances": "statlog_is", "configurations": 110, "value": [[324, 0, 3, 0, 3, 0, 0], [0, 330, 0, 0, 0, 0, 0], [1, 0, 307, 4, 14, 4, 0], [10, 0, 8, 269, 23, 20, 0], [8, 0, 40, 12, 265, 5, 0], [0, 0, 0, 0, 0, 330, 0], [0, 0, 0, 1, 0, 2, 327]]}, {"instances": "statlog_is", "configurations": 111, "value": [[324, 0, 3, 0, 3, 0, 0], [0, 330, 0, 0, 0, 0, 0], [0, 0, 313, 3, 12, 2, 0], [8, 0, 5, 281, 18, 18, 0], [4, 0, 29, 5, 287, 5, 0], [0, 0, 0, 0, 0, 330, 0], [0, 0, 0, 1, 0, 2, 327]]}, {"instances": "statlog_is", "configurations": 112, "value": [[325, 0, 1, 0, 4, 0, 0], [0, 330, 0, 0, 0, 0, 0], [1, 2, 321, 0, 5, 1, 0], [6, 0, 8, 274, 21, 21, 0], [6, 0, 41, 8, 274, 1, 0], [0, 0, 0, 0, 0, 330, 0], [0, 0, 1, 0, 0, 1, 328]]}, {"instances": "statlog_is", "configurations": 113, "value": [[326, 0, 0, 0, 4, 0, 0], [0, 330, 0, 0, 0, 0, 0], [0, 2, 321, 0, 7, 0, 0], [5, 0, 3, 284, 17, 21, 0], [4, 0, 31, 2, 292, 1, 0], [0, 0, 0, 0, 0, 330, 0], [0, 0, 1, 0, 0, 1, 328]]}, {"instances": "statlog_is", "configurations": 114, "value": [[326, 0, 0, 0, 4, 0, 0], [0, 330, 0, 0, 0, 0, 0], [2, 0, 307, 1, 18, 2, 0], [4, 0, 1, 269, 21, 34, 1], [2, 0, 25, 6, 297, 0, 0], [0, 0, 0, 5, 0, 325, 0], [0, 0, 0, 1, 0, 0, 329]]}, {"instances": "statlog_is", "configurations": 115, "value": [[329, 0, 0, 0, 1, 0, 0], [0, 330, 0, 0, 0, 0, 0], [2, 0, 310, 1, 15, 2, 0], [3, 0, 1, 275, 18, 32, 1], [2, 0, 18, 5, 305, 0, 0], [0, 0, 0, 2, 0, 328, 0], [0, 0, 0, 1, 0, 0, 329]]}, {"instances": "statlog_is", "configurations": 116, "value": [[322, 0, 2, 0, 5, 1, 0], [0, 328, 0, 0, 0, 2, 0], [1, 0, 302, 4, 16, 7, 0], [22, 1, 8, 253, 19, 27, 0], [19, 0, 37, 32, 234, 8, 0], [0, 0, 0, 1, 0, 329, 0], [3, 0, 0, 0, 3, 3, 321]]}, {"instances": "statlog_is", "configurations": 117, "value": [[325, 0, 2, 0, 2, 1, 0], [0, 328, 0, 0, 0, 2, 0], [1, 0, 308, 2, 13, 6, 0], [14, 1, 7, 273, 14, 21, 0], [11, 0, 26, 22, 263, 8, 0], [0, 0, 0, 0, 0, 330, 0], [0, 0, 0, 0, 3, 3, 324]]}, {"instances": "statlog_is", "configurations": 118, "value": [[322, 0, 4, 0, 4, 0, 0], [0, 330, 0, 0, 0, 0, 0], [1, 0, 316, 0, 10, 3, 0], [10, 1, 9, 270, 20, 20, 0], [8, 0, 46, 12, 259, 5, 0], [0, 0, 0, 0, 0, 330, 0], [0, 0, 0, 1, 0, 2, 327]]}, {"instances": "statlog_is", "configurations": 119, "value": [[325, 0, 1, 1, 3, 0, 0], [0, 330, 0, 0, 0, 0, 0], [0, 0, 323, 0, 7, 0, 0], [5, 1, 7, 288, 13, 16, 0], [4, 0, 26, 6, 289, 5, 0], [0, 0, 0, 0, 0, 330, 0], [0, 0, 0, 1, 0, 2, 327]]}, {"instances": "statlog_is", "configurations": 120, "value": [[327, 0, 0, 0, 3, 0, 0], [0, 330, 0, 0, 0, 0, 0], [3, 0, 302, 4, 16, 5, 0], [6, 0, 4, 275, 21, 24, 0], [4, 0, 37, 6, 283, 0, 0], [0, 0, 0, 0, 0, 330, 0], [0, 0, 1, 0, 1, 0, 328]]}, {"instances": "statlog_is", "configurations": 121, "value": [[328, 0, 0, 0, 2, 0, 0], [0, 330, 0, 0, 0, 0, 0], [1, 0, 315, 4, 8, 2, 0], [5, 0, 3, 286, 18, 18, 0], [4, 0, 32, 3, 291, 0, 0], [0, 0, 0, 0, 0, 330, 0], [0, 0, 1, 0, 0, 1, 328]]}, {"instances": "statlog_is", "configurations": 122, "value": [[322, 0, 3, 0, 5, 0, 0], [0, 330, 0, 0, 0, 0, 0], [1, 0, 300, 5, 19, 5, 0], [12, 0, 5, 263, 21, 29, 0], [12, 0, 35, 11, 266, 6, 0], [0, 0, 0, 0, 0, 330, 0], [0, 0, 0, 1, 0, 2, 327]]}, {"instances": "statlog_is", "configurations": 123, "value": [[324, 0, 3, 0, 3, 0, 0], [0, 330, 0, 0, 0, 0, 0], [1, 0, 309, 4, 13, 3, 0], [8, 0, 3, 282, 16, 21, 0], [8, 0, 27, 6, 283, 6, 0], [0, 0, 0, 0, 0, 330, 0], [0, 0, 0, 1, 0, 2, 327]]}, {"instances": "statlog_is", "configurations": 124, "value": [[323, 0, 2, 0, 5, 0, 0], [0, 330, 0, 0, 0, 0, 0], [3, 2, 309, 0, 15, 1, 0], [6, 0, 7, 262, 23, 32, 0], [6, 0, 40, 5, 278, 1, 0], [0, 0, 0, 0, 0, 330, 0], [0, 0, 1, 0, 1, 0, 328]]}, {"instances": "statlog_is", "configurations": 125, "value": [[326, 0, 2, 0, 2, 0, 0], [0, 330, 0, 0, 0, 0, 0], [1, 2, 319, 0, 8, 0, 0], [5, 0, 6, 275, 18, 26, 0], [5, 0, 32, 5, 287, 1, 0], [0, 0, 0, 0, 0, 330, 0], [0, 0, 1, 0, 0, 1, 328]]}, {"instances": "statlog_is", "configurations": 126, "value": [[325, 0, 0, 0, 5, 0, 0], [0, 330, 0, 0, 0, 0, 0], [4, 0, 298, 4, 20, 4, 0], [3, 0, 3, 264, 21, 38, 1], [2, 0, 26, 3, 299, 0, 0], [0, 0, 0, 1, 0, 329, 0], [0, 0, 0, 1, 0, 0, 329]]}, {"instances": "statlog_is", "configurations": 127, "value": [[327, 0, 0, 0, 3, 0, 0], [0, 330, 0, 0, 0, 0, 0], [2, 0, 308, 1, 15, 4, 0], [2, 0, 2, 275, 18, 32, 1], [2, 0, 18, 3, 307, 0, 0], [0, 0, 0, 1, 0, 329, 0], [0, 0, 0, 1, 0, 0, 329]]}, {"instances": "statlog_is", "configurations": 128, "value": [[323, 0, 2, 0, 4, 1, 0], [0, 328, 0, 0, 0, 2, 0], [6, 0, 295, 4, 15, 10, 0], [25, 1, 7, 249, 15, 33, 0], [28, 0, 37, 29, 224, 12, 0], [0, 0, 2, 2, 0, 326, 0], [3, 0, 2, 0, 1, 3, 321]]}, {"instances": "statlog_is", "configurations": 129, "value": [[326, 0, 2, 0, 1, 1, 0], [0, 328, 0, 0, 0, 2, 0], [2, 0, 307, 2, 13, 6, 0], [20, 0, 5, 267, 12, 26, 0], [14, 0, 25, 26, 254, 11, 0], [0, 0, 0, 0, 0, 330, 0], [0, 0, 1, 0, 2, 3, 324]]}, {"instances": "statlog_is", "configurations": 130, "value": [[321, 0, 3, 0, 6, 0, 0], [0, 330, 0, 0, 0, 0, 0], [1, 2, 308, 0, 14, 5, 0], [9, 2, 10, 264, 19, 26, 0], [12, 0, 42, 12, 259, 5, 0], [0, 0, 0, 0, 0, 330, 0], [0, 0, 0, 0, 0, 2, 328]]}, {"instances": "statlog_is", "configurations": 131, "value": [[325, 0, 2, 1, 2, 0, 0], [0, 330, 0, 0, 0, 0, 0], [1, 0, 320, 0, 7, 2, 0], [6, 1, 6, 287, 12, 18, 0], [6, 0, 31, 8, 280, 5, 0], [0, 0, 0, 0, 0, 330, 0], [0, 0, 0, 0, 0, 2, 328]]}, {"instances": "statlog_is", "configurations": 132, "value": [[327, 0, 0, 0, 3, 0, 0], [0, 330, 0, 0, 0, 0, 0], [3, 0, 296, 7, 21, 3, 0], [7, 0, 6, 274, 21, 22, 0], [5, 0, 46, 5, 274, 0, 0], [0, 0, 0, 0, 0, 330, 0], [0, 0, 1, 0, 1, 0, 328]]}, {"instances": "statlog_is", "configurations": 133, "value": [[327, 0, 0, 0, 3, 0, 0], [0, 330, 0, 0, 0, 0, 0], [1, 0, 315, 5, 8, 1, 0], [5, 0, 3, 284, 18, 20, 0], [5, 0, 34, 4, 287, 0, 0], [0, 0, 0, 0, 0, 330, 0], [0, 0, 1, 0, 0, 1, 328]]}, {"instances": "statlog_is", "configurations": 134, "value": [[323, 0, 3, 0, 4, 0, 0], [0, 330, 0, 0, 0, 0, 0], [3, 0, 301, 6, 15, 5, 0], [16, 0, 3, 262, 18, 31, 0], [17, 0, 47, 13, 247, 6, 0], [0, 0, 0, 0, 0, 330, 0], [0, 0, 0, 0, 0, 2, 328]]}, {"instances": "statlog_is", "configurations": 135, "value": [[325, 0, 3, 0, 2, 0, 0], [0, 330, 0, 0, 0, 0, 0], [1, 0, 310, 4, 11, 4, 0], [10, 0, 3, 279, 13, 25, 0], [10, 0, 30, 7, 277, 6, 0], [0, 0, 0, 0, 0, 330, 0], [0, 0, 0, 0, 0, 2, 328]]}, {"instances": "statlog_is", "configurations": 136, "value": [[324, 0, 2, 0, 4, 0, 0], [0, 330, 0, 0, 0, 0, 0], [3, 2, 309, 1, 15, 0, 0], [8, 0, 7, 259, 22, 34, 0], [6, 0, 52, 6, 264, 2, 0], [0, 0, 0, 0, 0, 330, 0], [0, 0, 1, 0, 1, 0, 328]]}, {"instances": "statlog_is", "configurations": 137, "value": [[326, 0, 2, 0, 2, 0, 0], [0, 330, 0, 0, 0, 0, 0], [1, 2, 319, 0, 8, 0, 0], [7, 0, 7, 270, 17, 29, 0], [6, 0, 35, 4, 283, 2, 0], [0, 0, 0, 0, 0, 330, 0], [0, 0, 1, 0, 1, 0, 328]]}, {"instances": "statlog_is", "configurations": 138, "value": [[325, 0, 0, 0, 5, 0, 0], [0, 330, 0, 0, 0, 0, 0], [3, 0, 296, 8, 17, 6, 0], [2, 0, 2, 261, 29, 35, 1], [2, 0, 28, 6, 294, 0, 0], [0, 0, 0, 3, 0, 327, 0], [0, 0, 0, 1, 0, 0, 329]]}, {"instances": "statlog_is", "configurations": 139, "value": [[327, 0, 0, 0, 3, 0, 0], [0, 330, 0, 0, 0, 0, 0], [2, 0, 304, 4, 16, 4, 0], [2, 0, 2, 274, 19, 32, 1], [2, 0, 19, 4, 305, 0, 0], [0, 0, 0, 1, 0, 329, 0], [0, 0, 0, 1, 0, 0, 329]]}, {"instances": "statlog_is", "configurations": 140, "value": [[324, 0, 2, 0, 1, 1, 2], [0, 328, 0, 0, 0, 2, 0], [8, 0, 287, 7, 18, 10, 0], [28, 1, 8, 245, 11, 37, 0], [29, 0, 51, 34, 205, 11, 0], [0, 0, 3, 1, 0, 326, 0], [2, 0, 3, 0, 0, 3, 322]]}, {"instances": "statlog_is", "configurations": 141, "value": [[326, 0, 2, 0, 1, 1, 0], [0, 328, 0, 0, 0, 2, 0], [4, 0, 299, 4, 16, 7, 0], [21, 1, 6, 266, 10, 26, 0], [16, 0, 30, 24, 249, 11, 0], [0, 0, 1, 0, 0, 329, 0], [0, 0, 2, 0, 1, 3, 324]]}, {"instances": "statlog_is", "configurations": 142, "value": [[320, 0, 3, 0, 7, 0, 0], [0, 330, 0, 0, 0, 0, 0], [2, 2, 308, 0, 13, 5, 0], [11, 2, 10, 257, 17, 33, 0], [13, 0, 51, 16, 245, 5, 0], [0, 0, 0, 0, 0, 330, 0], [0, 0, 0, 0, 0, 2, 328]]}, {"instances": "statlog_is", "configurations": 143, "value": [[325, 0, 2, 1, 2, 0, 0], [0, 330, 0, 0, 0, 0, 0], [1, 0, 319, 0, 8, 2, 0], [8, 1, 6, 282, 9, 24, 0], [6, 0, 29, 8, 282, 5, 0], [0, 0, 0, 0, 0, 330, 0], [0, 0, 0, 0, 0, 2, 328]]}, {"instances": "statlog_is", "configurations": 144, "value": [[327, 0, 0, 0, 3, 0, 0], [0, 330, 0, 0, 0, 0, 0], [3, 0, 294, 8, 21, 4, 0], [8, 0, 5, 269, 22, 26, 0], [6, 0, 41, 5, 277, 1, 0], [0, 0, 0, 0, 0, 330, 0], [0, 0, 1, 0, 0, 1, 328]]}, {"instances": "statlog_is", "configurations": 145, "value": [[328, 0, 0, 0, 2, 0, 0], [0, 330, 0, 0, 0, 0, 0], [1, 0, 313, 6, 9, 1, 0], [5, 0, 4, 283, 18, 20, 0], [5, 0, 32, 3, 290, 0, 0], [0, 0, 0, 0, 0, 330, 0], [0, 0, 1, 0, 0, 1, 328]]}, {"instances": "statlog_is", "configurations": 146, "value": [[323, 0, 3, 0, 4, 0, 0], [0, 330, 0, 0, 0, 0, 0], [4, 0, 297, 8, 16, 5, 0], [16, 0, 4, 258, 16, 36, 0], [19, 0, 51, 13, 240, 7, 0], [0, 0, 0, 0, 0, 330, 0], [0, 0, 0, 0, 0, 2, 328]]}, {"instances": "statlog_is", "configurations": 147, "value": [[325, 0, 3, 0, 2, 0, 0], [0, 330, 0, 0, 0, 0, 0], [1, 0, 307, 7, 12, 3, 0], [14, 0, 4, 276, 11, 25, 0], [10, 0, 36, 7, 270, 7, 0], [0, 0, 0, 0, 0, 330, 0], [0, 0, 0, 0, 0, 2, 328]]}, {"instances": "statlog_is", "configurations": 148, "value": [[327, 0, 0, 0, 3, 0, 0], [0, 330, 0, 0, 0, 0, 0], [4, 2, 306, 0, 17, 1, 0], [8, 0, 8, 252, 22, 40, 0], [7, 0, 49, 7, 265, 2, 0], [0, 0, 0, 0, 0, 330, 0], [0, 0, 2, 0, 0, 0, 328]]}, {"instances": "statlog_is", "configurations": 149, "value": [[328, 0, 0, 0, 2, 0, 0], [0, 330, 0, 0, 0, 0, 0], [1, 2, 318, 1, 7, 1, 0], [7, 0, 7, 268, 18, 30, 0], [6, 0, 36, 4, 282, 2, 0], [0, 0, 0, 0, 0, 330, 0], [0, 0, 2, 0, 0, 0, 328]]}, {"instances": "statlog_is", "configurations": 150, "value": [[324, 0, 0, 0, 6, 0, 0], [0, 330, 0, 0, 0, 0, 0], [4, 0, 288, 9, 23, 6, 0], [3, 0, 2, 245, 38, 41, 1], [3, 0, 27, 6, 294, 0, 0], [0, 0, 0, 3, 0, 327, 0], [0, 0, 0, 0, 0, 0, 330]]}, {"instances": "statlog_is", "configurations": 151, "value": [[327, 0, 0, 0, 3, 0, 0], [0, 330, 0, 0, 0, 0, 0], [2, 0, 302, 6, 15, 5, 0], [2, 0, 2, 267, 25, 33, 1], [2, 0, 22, 3, 303, 0, 0], [0, 0, 0, 2, 0, 328, 0], [0, 0, 0, 0, 0, 0, 330]]}, {"instances": "statlog_is", "configurations": 152, "value": [[326, 0, 3, 0, 1, 0, 0], [0, 324, 0, 4, 0, 2, 0], [11, 0, 276, 8, 17, 18, 0], [27, 1, 8, 243, 11, 40, 0], [29, 0, 51, 35, 200, 15, 0], [0, 0, 3, 0, 0, 327, 0], [2, 0, 3, 0, 0, 3, 322]]}, {"instances": "statlog_is", "configurations": 153, "value": [[326, 0, 2, 0, 1, 1, 0], [0, 328, 0, 0, 0, 2, 0], [7, 0, 290, 6, 15, 12, 0], [23, 1, 5, 262, 10, 29, 0], [17, 0, 36, 28, 236, 13, 0], [0, 0, 1, 0, 0, 329, 0], [0, 0, 3, 0, 0, 3, 324]]}, {"instances": "statlog_is", "configurations": 154, "value": [[320, 0, 5, 0, 5, 0, 0], [0, 330, 0, 0, 0, 0, 0], [2, 2, 307, 0, 15, 4, 0], [13, 1, 6, 257, 18, 35, 0], [20, 0, 56, 12, 236, 6, 0], [0, 0, 0, 0, 0, 330, 0], [0, 0, 0, 0, 0, 2, 328]]}, {"instances": "statlog_is", "configurations": 155, "value": [[325, 0, 3, 0, 2, 0, 0], [0, 330, 0, 0, 0, 0, 0], [1, 0, 319, 0, 9, 1, 0], [9, 1, 7, 278, 9, 26, 0], [7, 0, 32, 7, 279, 5, 0], [0, 0, 0, 0, 0, 330, 0], [0, 0, 0, 0, 0, 2, 328]]}, {"instances": "statlog_is", "configurations": 156, "value": [[328, 0, 0, 0, 2, 0, 0], [0, 330, 0, 0, 0, 0, 0], [4, 0, 289, 7, 22, 8, 0], [8, 0, 4, 260, 28, 30, 0], [6, 0, 47, 6, 270, 1, 0], [0, 0, 0, 0, 0, 330, 0], [0, 0, 1, 0, 0, 1, 328]]}, {"instances": "statlog_is", "configurations": 157, "value": [[328, 0, 0, 0, 2, 0, 0], [0, 330, 0, 0, 0, 0, 0], [2, 0, 307, 5, 12, 4, 0], [6, 0, 3, 280, 19, 22, 0], [6, 0, 32, 4, 288, 0, 0], [0, 0, 0, 0, 0, 330, 0], [0, 0, 1, 0, 0, 1, 328]]}, {"instances": "statlog_is", "configurations": 158, "value": [[324, 0, 1, 0, 3, 2, 0], [0, 330, 0, 0, 0, 0, 0], [7, 0, 288, 7, 22, 6, 0], [19, 0, 2, 252, 18, 39, 0], [25, 0, 55, 13, 230, 7, 0], [0, 0, 0, 0, 0, 330, 0], [0, 0, 0, 0, 0, 2, 328]]}, {"instances": "statlog_is", "configurations": 159, "value": [[325, 0, 3, 0, 2, 0, 0], [0, 330, 0, 0, 0, 0, 0], [2, 0, 305, 6, 14, 3, 0], [15, 0, 2, 268, 13, 32, 0], [15, 0, 38, 8, 263, 6, 0], [0, 0, 0, 0, 0, 330, 0], [0, 0, 0, 0, 0, 2, 328]]}, {"instances": "statlog_is", "configurations": 160, "value": [[328, 0, 0, 0, 2, 0, 0], [0, 330, 0, 0, 0, 0, 0], [4, 2, 302, 1, 20, 1, 0], [10, 0, 8, 244, 25, 43, 0], [6, 0, 56, 6, 260, 2, 0], [0, 0, 0, 0, 0, 330, 0], [0, 0, 2, 0, 0, 0, 328]]}, {"instances": "statlog_is", "configurations": 161, "value": [[328, 0, 0, 0, 2, 0, 0], [0, 330, 0, 0, 0, 0, 0], [1, 2, 317, 1, 8, 1, 0], [8, 0, 8, 265, 17, 32, 0], [6, 0, 40, 5, 277, 2, 0], [0, 0, 0, 0, 0, 330, 0], [0, 0, 2, 0, 0, 0, 328]]}, {"instances": "statlog_is", "configurations": 162, "value": [[323, 0, 0, 0, 7, 0, 0], [0, 330, 0, 0, 0, 0, 0], [4, 1, 280, 9, 27, 9, 0], [2, 0, 2, 248, 36, 40, 2], [3, 0, 29, 5, 293, 0, 0], [0, 0, 0, 4, 0, 326, 0], [0, 0, 0, 0, 1, 0, 329]]}, {"instances": "statlog_is", "configurations": 163, "value": [[326, 0, 0, 0, 4, 0, 0], [0, 330, 0, 0, 0, 0, 0], [2, 0, 295, 7, 19, 7, 0], [2, 0, 2, 263, 29, 33, 1], [2, 0, 21, 2, 305, 0, 0], [0, 0, 0, 2, 0, 328, 0], [0, 0, 0, 0, 1, 0, 329]]}, {"instances": "statlog_is", "configurations": 164, "value": [[326, 0, 2, 0, 1, 1, 0], [0, 320, 0, 8, 0, 2, 0], [14, 0, 268, 8, 19, 21, 0], [27, 1, 7, 238, 14, 43, 0], [31, 0, 52, 37, 194, 16, 0], [0, 0, 5, 0, 0, 325, 0], [0, 0, 3, 0, 0, 3, 324]]}, {"instances": "statlog_is", "configurations": 165, "value": [[326, 0, 2, 0, 1, 1, 0], [0, 328, 0, 0, 0, 2, 0], [7, 0, 290, 5, 15, 13, 0], [22, 1, 6, 258, 9, 34, 0], [19, 0, 35, 27, 233, 16, 0], [0, 0, 0, 0, 0, 330, 0], [0, 0, 3, 0, 0, 3, 324]]}, {"instances": "statlog_is", "configurations": 166, "value": [[322, 0, 3, 0, 5, 0, 0], [0, 330, 0, 0, 0, 0, 0], [6, 2, 302, 2, 13, 5, 0], [14, 3, 6, 254, 17, 36, 0], [24, 0, 61, 13, 226, 6, 0], [0, 0, 0, 0, 0, 330, 0], [0, 0, 0, 0, 0, 2, 328]]}, {"instances": "statlog_is", "configurations": 167, "value": [[325, 0, 3, 0, 2, 0, 0], [0, 330, 0, 0, 0, 0, 0], [2, 0, 317, 0, 9, 2, 0], [8, 1, 6, 280, 9, 26, 0], [10, 0, 33, 7, 275, 5, 0], [0, 0, 0, 0, 0, 330, 0], [0, 0, 0, 0, 0, 2, 328]]}]