[{"instances": "tao", "configurations": 0, "value": [[730, 214], [195, 749]]}, {"instances": "tao", "configurations": 1, "value": [[738, 206], [198, 746]]}, {"instances": "tao", "configurations": 2, "value": [[733, 211], [195, 749]]}, {"instances": "tao", "configurations": 3, "value": [[731, 213], [197, 747]]}, {"instances": "tao", "configurations": 4, "value": [[729, 215], [200, 744]]}, {"instances": "tao", "configurations": 5, "value": [[721, 223], [167, 777]]}, {"instances": "tao", "configurations": 6, "value": [[727, 217], [135, 809]]}, {"instances": "tao", "configurations": 7, "value": [[714, 230], [127, 817]]}, {"instances": "tao", "configurations": 8, "value": [[730, 214], [201, 743]]}, {"instances": "tao", "configurations": 9, "value": [[715, 229], [144, 800]]}, {"instances": "tao", "configurations": 10, "value": [[699, 245], [202, 742]]}, {"instances": "tao", "configurations": 11, "value": [[747, 197], [175, 769]]}, {"instances": "tao", "configurations": 12, "value": [[740, 204], [178, 766]]}, {"instances": "tao", "configurations": 13, "value": [[700, 244], [158, 786]]}, {"instances": "tao", "configurations": 14, "value": [[699, 245], [117, 827]]}, {"instances": "tao", "configurations": 15, "value": [[731, 213], [199, 745]]}, {"instances": "tao", "configurations": 16, "value": [[731, 213], [196, 748]]}, {"instances": "tao", "configurations": 17, "value": [[724, 220], [213, 731]]}, {"instances": "tao", "configurations": 18, "value": [[743, 201], [183, 761]]}, {"instances": "tao", "configurations": 19, "value": [[729, 215], [205, 739]]}, {"instances": "tao", "configurations": 20, "value": [[719, 225], [200, 744]]}, {"instances": "tao", "configurations": 21, "value": [[686, 258], [133, 811]]}, {"instances": "tao", "configurations": 22, "value": [[736, 208], [209, 735]]}, {"instances": "tao", "configurations": 23, "value": [[721, 223], [202, 742]]}, {"instances": "tao", "configurations": 24, "value": [[730, 214], [198, 746]]}, {"instances": "tao", "configurations": 25, "value": [[760, 184], [259, 685]]}, {"instances": "tao", "configurations": 26, "value": [[747, 197], [174, 770]]}, {"instances": "tao", "configurations": 27, "value": [[742, 202], [164, 780]]}, {"instances": "tao", "configurations": 28, "value": [[724, 220], [135, 809]]}, {"instances": "tao", "configurations": 29, "value": [[630, 314], [43, 901]]}, {"instances": "tao", "configurations": 30, "value": [[219, 725], [828, 116]]}, {"instances": "tao", "configurations": 31, "value": [[748, 196], [178, 766]]}, {"instances": "tao", "configurations": 32, "value": [[738, 206], [179, 765]]}, {"instances": "tao", "configurations": 33, "value": [[735, 209], [179, 765]]}, {"instances": "tao", "configurations": 34, "value": [[737, 207], [209, 735]]}, {"instances": "tao", "configurations": 35, "value": [[719, 225], [146, 798]]}, {"instances": "tao", "configurations": 36, "value": [[727, 217], [203, 741]]}, {"instances": "tao", "configurations": 37, "value": [[736, 208], [187, 757]]}, {"instances": "tao", "configurations": 38, "value": [[730, 214], [195, 749]]}, {"instances": "tao", "configurations": 39, "value": [[693, 251], [217, 727]]}, {"instances": "tao", "configurations": 40, "value": [[737, 207], [211, 733]]}, {"instances": "tao", "configurations": 41, "value": [[730, 214], [205, 739]]}, {"instances": "tao", "configurations": 42, "value": [[712, 232], [126, 818]]}, {"instances": "tao", "configurations": 43, "value": [[135, 809], [824, 120]]}, {"instances": "tao", "configurations": 44, "value": [[763, 181], [246, 698]]}, {"instances": "tao", "configurations": 45, "value": [[133, 811], [810, 134]]}, {"instances": "tao", "configurations": 46, "value": [[738, 206], [190, 754]]}, {"instances": "tao", "configurations": 47, "value": [[744, 200], [177, 767]]}, {"instances": "tao", "configurations": 48, "value": [[680, 264], [244, 700]]}, {"instances": "tao", "configurations": 49, "value": [[714, 230], [131, 813]]}, {"instances": "tao", "configurations": 50, "value": [[731, 213], [204, 740]]}, {"instances": "tao", "configurations": 51, "value": [[648, 296], [461, 483]]}, {"instances": "tao", "configurations": 52, "value": [[702, 242], [248, 696]]}, {"instances": "tao", "configurations": 53, "value": [[746, 198], [172, 772]]}, {"instances": "tao", "configurations": 54, "value": [[741, 203], [179, 765]]}, {"instances": "tao", "configurations": 55, "value": [[729, 215], [194, 750]]}, {"instances": "tao", "configurations": 56, "value": [[638, 306], [95, 849]]}, {"instances": "tao", "configurations": 57, "value": [[640, 304], [136, 808]]}, {"instances": "tao", "configurations": 58, "value": [[732, 212], [197, 747]]}, {"instances": "tao", "configurations": 59, "value": [[731, 213], [198, 746]]}, {"instances": "tao", "configurations": 60, "value": [[751, 193], [98, 846]]}, {"instances": "tao", "configurations": 61, "value": [[726, 218], [195, 749]]}, {"instances": "tao", "configurations": 62, "value": [[738, 206], [155, 789]]}, {"instances": "tao", "configurations": 63, "value": [[731, 213], [143, 801]]}, {"instances": "tao", "configurations": 64, "value": [[655, 289], [125, 819]]}, {"instances": "tao", "configurations": 65, "value": [[727, 217], [208, 736]]}, {"instances": "tao", "configurations": 66, "value": [[729, 215], [203, 741]]}, {"instances": "tao", "configurations": 67, "value": [[746, 198], [176, 768]]}, {"instances": "tao", "configurations": 68, "value": [[766, 178], [295, 649]]}, {"instances": "tao", "configurations": 69, "value": [[746, 198], [167, 777]]}, {"instances": "tao", "configurations": 70, "value": [[717, 227], [124, 820]]}, {"instances": "tao", "configurations": 71, "value": [[544, 400], [203, 741]]}, {"instances": "tao", "configurations": 72, "value": [[733, 211], [203, 741]]}, {"instances": "tao", "configurations": 73, "value": [[743, 201], [182, 762]]}, {"instances": "tao", "configurations": 74, "value": [[738, 206], [177, 767]]}, {"instances": "tao", "configurations": 75, "value": [[734, 210], [201, 743]]}, {"instances": "tao", "configurations": 76, "value": [[720, 224], [159, 785]]}, {"instances": "tao", "configurations": 77, "value": [[697, 247], [120, 824]]}, {"instances": "tao", "configurations": 78, "value": [[731, 213], [213, 731]]}, {"instances": "tao", "configurations": 79, "value": [[739, 205], [199, 745]]}, {"instances": "tao", "configurations": 80, "value": [[734, 210], [190, 754]]}, {"instances": "tao", "configurations": 81, "value": [[728, 216], [196, 748]]}, {"instances": "tao", "configurations": 82, "value": [[746, 198], [173, 771]]}, {"instances": "tao", "configurations": 83, "value": [[734, 210], [147, 797]]}, {"instances": "tao", "configurations": 84, "value": [[731, 213], [146, 798]]}, {"instances": "tao", "configurations": 85, "value": [[733, 211], [188, 756]]}, {"instances": "tao", "configurations": 86, "value": [[734, 210], [186, 758]]}, {"instances": "tao", "configurations": 87, "value": [[731, 213], [193, 751]]}, {"instances": "tao", "configurations": 88, "value": [[732, 212], [192, 752]]}, {"instances": "tao", "configurations": 89, "value": [[739, 205], [180, 764]]}, {"instances": "tao", "configurations": 90, "value": [[700, 244], [155, 789]]}, {"instances": "tao", "configurations": 91, "value": [[710, 234], [124, 820]]}, {"instances": "tao", "configurations": 92, "value": [[729, 215], [203, 741]]}, {"instances": "tao", "configurations": 93, "value": [[745, 199], [183, 761]]}, {"instances": "tao", "configurations": 94, "value": [[730, 214], [195, 749]]}, {"instances": "tao", "configurations": 95, "value": [[732, 212], [194, 750]]}, {"instances": "tao", "configurations": 96, "value": [[699, 245], [140, 804]]}, {"instances": "tao", "configurations": 97, "value": [[732, 212], [211, 733]]}, {"instances": "tao", "configurations": 98, "value": [[689, 255], [121, 823]]}, {"instances": "tao", "configurations": 99, "value": [[732, 212], [198, 746]]}, {"instances": "tao", "configurations": 100, "value": [[691, 253], [133, 811]]}, {"instances": "tao", "configurations": 101, "value": [[735, 209], [213, 731]]}, {"instances": "tao", "configurations": 102, "value": [[729, 215], [203, 741]]}, {"instances": "tao", "configurations": 103, "value": [[745, 199], [174, 770]]}, {"instances": "tao", "configurations": 104, "value": [[737, 207], [153, 791]]}, {"instances": "tao", "configurations": 105, "value": [[725, 219], [134, 810]]}, {"instances": "tao", "configurations": 106, "value": [[731, 213], [199, 745]]}, {"instances": "tao", "configurations": 107, "value": [[714, 230], [202, 742]]}, {"instances": "tao", "configurations": 108, "value": [[831, 113], [271, 673]]}, {"instances": "tao", "configurations": 109, "value": [[748, 196], [174, 770]]}, {"instances": "tao", "configurations": 110, "value": [[737, 207], [176, 768]]}, {"instances": "tao", "configurations": 111, "value": [[682, 262], [135, 809]]}, {"instances": "tao", "configurations": 112, "value": [[695, 249], [116, 828]]}, {"instances": "tao", "configurations": 113, "value": [[720, 224], [228, 716]]}, {"instances": "tao", "configurations": 114, "value": [[733, 211], [197, 747]]}, {"instances": "tao", "configurations": 115, "value": [[770, 174], [317, 627]]}, {"instances": "tao", "configurations": 116, "value": [[727, 217], [204, 740]]}, {"instances": "tao", "configurations": 117, "value": [[681, 263], [194, 750]]}, {"instances": "tao", "configurations": 118, "value": [[742, 202], [160, 784]]}, {"instances": "tao", "configurations": 119, "value": [[660, 284], [108, 836]]}, {"instances": "tao", "configurations": 120, "value": [[737, 207], [208, 736]]}, {"instances": "tao", "configurations": 121, "value": [[146, 798], [810, 134]]}, {"instances": "tao", "configurations": 122, "value": [[698, 246], [230, 714]]}, {"instances": "tao", "configurations": 123, "value": [[614, 330], [295, 649]]}, {"instances": "tao", "configurations": 124, "value": [[745, 199], [168, 776]]}, {"instances": "tao", "configurations": 125, "value": [[738, 206], [175, 769]]}, {"instances": "tao", "configurations": 126, "value": [[709, 235], [129, 815]]}, {"instances": "tao", "configurations": 127, "value": [[700, 244], [156, 788]]}, {"instances": "tao", "configurations": 128, "value": [[745, 199], [178, 766]]}, {"instances": "tao", "configurations": 129, "value": [[734, 210], [182, 762]]}, {"instances": "tao", "configurations": 130, "value": [[731, 213], [193, 751]]}, {"instances": "tao", "configurations": 131, "value": [[731, 213], [189, 755]]}, {"instances": "tao", "configurations": 132, "value": [[730, 214], [201, 743]]}, {"instances": "tao", "configurations": 133, "value": [[713, 231], [128, 816]]}, {"instances": "tao", "configurations": 134, "value": [[633, 311], [117, 827]]}, {"instances": "tao", "configurations": 135, "value": [[730, 214], [199, 745]]}, {"instances": "tao", "configurations": 136, "value": [[742, 202], [190, 754]]}, {"instances": "tao", "configurations": 137, "value": [[727, 217], [209, 735]]}, {"instances": "tao", "configurations": 138, "value": [[745, 199], [166, 778]]}, {"instances": "tao", "configurations": 139, "value": [[727, 217], [138, 806]]}, {"instances": "tao", "configurations": 140, "value": [[710, 234], [124, 820]]}, {"instances": "tao", "configurations": 141, "value": [[727, 217], [206, 738]]}, {"instances": "tao", "configurations": 142, "value": [[714, 230], [178, 766]]}, {"instances": "tao", "configurations": 143, "value": [[740, 204], [180, 764]]}, {"instances": "tao", "configurations": 144, "value": [[741, 203], [174, 770]]}, {"instances": "tao", "configurations": 145, "value": [[769, 175], [245, 699]]}, {"instances": "tao", "configurations": 146, "value": [[731, 213], [201, 743]]}, {"instances": "tao", "configurations": 147, "value": [[723, 221], [193, 751]]}, {"instances": "tao", "configurations": 148, "value": [[696, 248], [170, 774]]}, {"instances": "tao", "configurations": 149, "value": [[747, 197], [178, 766]]}, {"instances": "tao", "configurations": 150, "value": [[745, 199], [180, 764]]}, {"instances": "tao", "configurations": 151, "value": [[731, 213], [197, 747]]}, {"instances": "tao", "configurations": 152, "value": [[731, 213], [196, 748]]}, {"instances": "tao", "configurations": 153, "value": [[715, 229], [200, 744]]}, {"instances": "tao", "configurations": 154, "value": [[626, 318], [97, 847]]}, {"instances": "tao", "configurations": 155, "value": [[734, 210], [213, 731]]}, {"instances": "tao", "configurations": 156, "value": [[731, 213], [204, 740]]}, {"instances": "tao", "configurations": 157, "value": [[707, 237], [259, 685]]}, {"instances": "tao", "configurations": 158, "value": [[747, 197], [173, 771]]}, {"instances": "tao", "configurations": 159, "value": [[747, 197], [176, 768]]}, {"instances": "tao", "configurations": 160, "value": [[742, 202], [165, 779]]}, {"instances": "tao", "configurations": 161, "value": [[729, 215], [177, 767]]}, {"instances": "tao", "configurations": 162, "value": [[252, 692], [473, 471]]}, {"instances": "tao", "configurations": 163, "value": [[742, 202], [199, 745]]}, {"instances": "tao", "configurations": 164, "value": [[733, 211], [194, 750]]}, {"instances": "tao", "configurations": 165, "value": [[631, 313], [144, 800]]}, {"instances": "tao", "configurations": 166, "value": [[769, 175], [217, 727]]}, {"instances": "tao", "configurations": 167, "value": [[738, 206], [155, 789]]}, {"instances": "tao", "configurations": 168, "value": [[710, 234], [124, 820]]}, {"instances": "tao", "configurations": 169, "value": [[126, 818], [810, 134]]}, {"instances": "tao", "configurations": 170, "value": [[748, 196], [348, 596]]}, {"instances": "tao", "configurations": 171, "value": [[134, 810], [810, 134]]}, {"instances": "tao", "configurations": 172, "value": [[744, 200], [170, 774]]}, {"instances": "tao", "configurations": 173, "value": [[740, 204], [179, 765]]}, {"instances": "tao", "configurations": 174, "value": [[193, 751], [692, 252]]}, {"instances": "tao", "configurations": 175, "value": [[726, 218], [158, 786]]}, {"instances": "tao", "configurations": 176, "value": [[725, 219], [229, 715]]}, {"instances": "tao", "configurations": 177, "value": [[736, 208], [185, 759]]}, {"instances": "tao", "configurations": 178, "value": [[739, 205], [198, 746]]}, {"instances": "tao", "configurations": 179, "value": [[737, 207], [214, 730]]}, {"instances": "tao", "configurations": 180, "value": [[738, 206], [184, 760]]}, {"instances": "tao", "configurations": 181, "value": [[743, 201], [161, 783]]}, {"instances": "tao", "configurations": 182, "value": [[709, 235], [124, 820]]}, {"instances": "tao", "configurations": 183, "value": [[730, 214], [203, 741]]}, {"instances": "tao", "configurations": 184, "value": [[730, 214], [211, 733]]}, {"instances": "tao", "configurations": 185, "value": [[739, 205], [235, 709]]}, {"instances": "tao", "configurations": 186, "value": [[654, 290], [227, 717]]}, {"instances": "tao", "configurations": 187, "value": [[746, 198], [177, 767]]}, {"instances": "tao", "configurations": 188, "value": [[735, 209], [180, 764]]}, {"instances": "tao", "configurations": 189, "value": [[579, 365], [51, 893]]}, {"instances": "tao", "configurations": 190, "value": [[725, 219], [235, 709]]}, {"instances": "tao", "configurations": 191, "value": [[732, 212], [195, 749]]}, {"instances": "tao", "configurations": 192, "value": [[740, 204], [180, 764]]}, {"instances": "tao", "configurations": 193, "value": [[734, 210], [181, 763]]}, {"instances": "tao", "configurations": 194, "value": [[731, 213], [196, 748]]}, {"instances": "tao", "configurations": 195, "value": [[705, 239], [180, 764]]}, {"instances": "tao", "configurations": 196, "value": [[719, 225], [128, 816]]}, {"instances": "tao", "configurations": 197, "value": [[730, 214], [196, 748]]}, {"instances": "tao", "configurations": 198, "value": [[704, 240], [215, 729]]}, {"instances": "tao", "configurations": 199, "value": [[745, 199], [189, 755]]}, {"instances": "tao", "configurations": 200, "value": [[732, 212], [210, 734]]}, {"instances": "tao", "configurations": 201, "value": [[743, 201], [166, 778]]}, {"instances": "tao", "configurations": 202, "value": [[689, 255], [153, 791]]}, {"instances": "tao", "configurations": 203, "value": [[724, 220], [134, 810]]}, {"instances": "tao", "configurations": 204, "value": [[766, 178], [292, 652]]}, {"instances": "tao", "configurations": 205, "value": [[150, 794], [891, 53]]}, {"instances": "tao", "configurations": 206, "value": [[751, 193], [179, 765]]}, {"instances": "tao", "configurations": 207, "value": [[747, 197], [173, 771]]}, {"instances": "tao", "configurations": 208, "value": [[309, 635], [686, 258]]}, {"instances": "tao", "configurations": 209, "value": [[734, 210], [156, 788]]}, {"instances": "tao", "configurations": 210, "value": [[744, 200], [241, 703]]}, {"instances": "tao", "configurations": 211, "value": [[732, 212], [199, 745]]}, {"instances": "tao", "configurations": 212, "value": [[140, 804], [807, 137]]}, {"instances": "tao", "configurations": 213, "value": [[702, 242], [249, 695]]}, {"instances": "tao", "configurations": 214, "value": [[740, 204], [176, 768]]}, {"instances": "tao", "configurations": 215, "value": [[626, 318], [292, 652]]}, {"instances": "tao", "configurations": 216, "value": [[736, 208], [194, 750]]}, {"instances": "tao", "configurations": 217, "value": [[723, 221], [174, 770]]}, {"instances": "tao", "configurations": 218, "value": [[739, 205], [181, 763]]}, {"instances": "tao", "configurations": 219, "value": [[730, 214], [204, 740]]}, {"instances": "tao", "configurations": 220, "value": [[739, 205], [194, 750]]}, {"instances": "tao", "configurations": 221, "value": [[730, 214], [198, 746]]}, {"instances": "tao", "configurations": 222, "value": [[720, 224], [194, 750]]}, {"instances": "tao", "configurations": 223, "value": [[743, 201], [166, 778]]}, {"instances": "tao", "configurations": 224, "value": [[708, 236], [122, 822]]}, {"instances": "tao", "configurations": 225, "value": [[716, 228], [237, 707]]}, {"instances": "tao", "configurations": 226, "value": [[716, 228], [139, 805]]}, {"instances": "tao", "configurations": 227, "value": [[727, 217], [205, 739]]}, {"instances": "tao", "configurations": 228, "value": [[747, 197], [174, 770]]}, {"instances": "tao", "configurations": 229, "value": [[737, 207], [180, 764]]}, {"instances": "tao", "configurations": 230, "value": [[736, 208], [178, 766]]}, {"instances": "tao", "configurations": 231, "value": [[720, 224], [140, 804]]}, {"instances": "tao", "configurations": 232, "value": [[732, 212], [199, 745]]}, {"instances": "tao", "configurations": 233, "value": [[736, 208], [183, 761]]}, {"instances": "tao", "configurations": 234, "value": [[736, 208], [185, 759]]}, {"instances": "tao", "configurations": 235, "value": [[736, 208], [185, 759]]}, {"instances": "tao", "configurations": 236, "value": [[657, 287], [201, 743]]}, {"instances": "tao", "configurations": 237, "value": [[729, 215], [189, 755]]}, {"instances": "tao", "configurations": 238, "value": [[730, 214], [140, 804]]}, {"instances": "tao", "configurations": 239, "value": [[738, 206], [206, 738]]}, {"instances": "tao", "configurations": 240, "value": [[739, 205], [199, 745]]}, {"instances": "tao", "configurations": 241, "value": [[710, 234], [213, 731]]}, {"instances": "tao", "configurations": 242, "value": [[738, 206], [182, 762]]}, {"instances": "tao", "configurations": 243, "value": [[746, 198], [173, 771]]}, {"instances": "tao", "configurations": 244, "value": [[743, 201], [170, 774]]}, {"instances": "tao", "configurations": 245, "value": [[635, 309], [97, 847]]}, {"instances": "tao", "configurations": 246, "value": [[124, 820], [816, 128]]}, {"instances": "tao", "configurations": 247, "value": [[715, 229], [203, 741]]}, {"instances": "tao", "configurations": 248, "value": [[746, 198], [177, 767]]}, {"instances": "tao", "configurations": 249, "value": [[128, 816], [794, 150]]}, {"instances": "tao", "configurations": 250, "value": [[739, 205], [192, 752]]}, {"instances": "tao", "configurations": 251, "value": [[730, 214], [183, 761]]}, {"instances": "tao", "configurations": 252, "value": [[716, 228], [196, 748]]}, {"instances": "tao", "configurations": 253, "value": [[709, 235], [166, 778]]}, {"instances": "tao", "configurations": 254, "value": [[548, 396], [122, 822]]}, {"instances": "tao", "configurations": 255, "value": [[679, 265], [223, 721]]}, {"instances": "tao", "configurations": 256, "value": [[737, 207], [180, 764]]}, {"instances": "tao", "configurations": 257, "value": [[723, 221], [210, 734]]}, {"instances": "tao", "configurations": 258, "value": [[134, 810], [810, 134]]}, {"instances": "tao", "configurations": 259, "value": [[707, 237], [121, 823]]}, {"instances": "tao", "configurations": 260, "value": [[726, 218], [221, 723]]}, {"instances": "tao", "configurations": 261, "value": [[743, 201], [178, 766]]}, {"instances": "tao", "configurations": 262, "value": [[739, 205], [181, 763]]}, {"instances": "tao", "configurations": 263, "value": [[702, 242], [133, 811]]}, {"instances": "tao", "configurations": 264, "value": [[737, 207], [186, 758]]}, {"instances": "tao", "configurations": 265, "value": [[696, 248], [237, 707]]}, {"instances": "tao", "configurations": 266, "value": [[693, 251], [120, 824]]}, {"instances": "tao", "configurations": 267, "value": [[730, 214], [196, 748]]}, {"instances": "tao", "configurations": 268, "value": [[732, 212], [198, 746]]}, {"instances": "tao", "configurations": 269, "value": [[737, 207], [208, 736]]}, {"instances": "tao", "configurations": 270, "value": [[730, 214], [195, 749]]}, {"instances": "tao", "configurations": 271, "value": [[727, 217], [203, 741]]}, {"instances": "tao", "configurations": 272, "value": [[699, 245], [159, 785]]}, {"instances": "tao", "configurations": 273, "value": [[699, 245], [120, 824]]}, {"instances": "tao", "configurations": 274, "value": [[729, 215], [203, 741]]}, {"instances": "tao", "configurations": 275, "value": [[658, 286], [166, 778]]}, {"instances": "tao", "configurations": 276, "value": [[721, 223], [219, 725]]}, {"instances": "tao", "configurations": 277, "value": [[747, 197], [176, 768]]}, {"instances": "tao", "configurations": 278, "value": [[746, 198], [248, 696]]}, {"instances": "tao", "configurations": 279, "value": [[736, 208], [151, 793]]}, {"instances": "tao", "configurations": 280, "value": [[721, 223], [139, 805]]}, {"instances": "tao", "configurations": 281, "value": [[730, 214], [212, 732]]}, {"instances": "tao", "configurations": 282, "value": [[737, 207], [199, 745]]}, {"instances": "tao", "configurations": 283, "value": [[619, 325], [134, 810]]}, {"instances": "tao", "configurations": 284, "value": [[746, 198], [174, 770]]}, {"instances": "tao", "configurations": 285, "value": [[743, 201], [166, 778]]}, {"instances": "tao", "configurations": 286, "value": [[733, 211], [148, 796]]}, {"instances": "tao", "configurations": 287, "value": [[727, 217], [135, 809]]}, {"instances": "tao", "configurations": 288, "value": [[712, 232], [325, 619]]}, {"instances": "tao", "configurations": 289, "value": [[140, 804], [814, 130]]}, {"instances": "tao", "configurations": 290, "value": [[745, 199], [179, 765]]}, {"instances": "tao", "configurations": 291, "value": [[740, 204], [175, 769]]}, {"instances": "tao", "configurations": 292, "value": [[726, 218], [204, 740]]}, {"instances": "tao", "configurations": 293, "value": [[738, 206], [285, 659]]}, {"instances": "tao", "configurations": 294, "value": [[657, 287], [175, 769]]}, {"instances": "tao", "configurations": 295, "value": [[735, 209], [204, 740]]}, {"instances": "tao", "configurations": 296, "value": [[178, 766], [786, 158]]}, {"instances": "tao", "configurations": 297, "value": [[134, 810], [810, 134]]}, {"instances": "tao", "configurations": 298, "value": [[129, 815], [811, 133]]}, {"instances": "tao", "configurations": 299, "value": [[741, 203], [171, 773]]}, {"instances": "tao", "configurations": 300, "value": [[732, 212], [148, 796]]}, {"instances": "tao", "configurations": 301, "value": [[132, 812], [800, 144]]}, {"instances": "tao", "configurations": 302, "value": [[737, 207], [207, 737]]}, {"instances": "tao", "configurations": 303, "value": [[731, 213], [204, 740]]}, {"instances": "tao", "configurations": 304, "value": [[771, 173], [219, 725]]}, {"instances": "tao", "configurations": 305, "value": [[771, 173], [217, 727]]}, {"instances": "tao", "configurations": 306, "value": [[694, 250], [131, 813]]}, {"instances": "tao", "configurations": 307, "value": [[742, 202], [161, 783]]}, {"instances": "tao", "configurations": 308, "value": [[722, 222], [131, 813]]}, {"instances": "tao", "configurations": 309, "value": [[727, 217], [201, 743]]}, {"instances": "tao", "configurations": 310, "value": [[772, 172], [484, 460]]}, {"instances": "tao", "configurations": 311, "value": [[751, 193], [179, 765]]}, {"instances": "tao", "configurations": 312, "value": [[737, 207], [178, 766]]}, {"instances": "tao", "configurations": 313, "value": [[734, 210], [187, 757]]}, {"instances": "tao", "configurations": 314, "value": [[734, 210], [182, 762]]}, {"instances": "tao", "configurations": 315, "value": [[713, 231], [125, 819]]}, {"instances": "tao", "configurations": 316, "value": [[731, 213], [198, 746]]}, {"instances": "tao", "configurations": 317, "value": [[735, 209], [186, 758]]}, {"instances": "tao", "configurations": 318, "value": [[701, 243], [190, 754]]}, {"instances": "tao", "configurations": 319, "value": [[732, 212], [191, 753]]}, {"instances": "tao", "configurations": 320, "value": [[719, 225], [206, 738]]}, {"instances": "tao", "configurations": 321, "value": [[733, 211], [147, 797]]}, {"instances": "tao", "configurations": 322, "value": [[576, 368], [157, 787]]}, {"instances": "tao", "configurations": 323, "value": [[729, 215], [203, 741]]}, {"instances": "tao", "configurations": 324, "value": [[714, 230], [227, 717]]}, {"instances": "tao", "configurations": 325, "value": [[765, 179], [187, 757]]}, {"instances": "tao", "configurations": 326, "value": [[841, 103], [267, 677]]}, {"instances": "tao", "configurations": 327, "value": [[743, 201], [173, 771]]}, {"instances": "tao", "configurations": 328, "value": [[737, 207], [152, 792]]}, {"instances": "tao", "configurations": 329, "value": [[727, 217], [175, 769]]}, {"instances": "tao", "configurations": 330, "value": [[367, 577], [508, 436]]}, {"instances": "tao", "configurations": 331, "value": [[735, 209], [185, 759]]}, {"instances": "tao", "configurations": 332, "value": [[711, 233], [265, 679]]}, {"instances": "tao", "configurations": 333, "value": [[744, 200], [180, 764]]}, {"instances": "tao", "configurations": 334, "value": [[728, 216], [204, 740]]}, {"instances": "tao", "configurations": 335, "value": [[736, 208], [191, 753]]}, {"instances": "tao", "configurations": 336, "value": [[724, 220], [133, 811]]}, {"instances": "tao", "configurations": 337, "value": [[134, 810], [810, 134]]}, {"instances": "tao", "configurations": 338, "value": [[735, 209], [88, 856]]}, {"instances": "tao", "configurations": 339, "value": [[744, 200], [177, 767]]}, {"instances": "tao", "configurations": 340, "value": [[740, 204], [178, 766]]}, {"instances": "tao", "configurations": 341, "value": [[728, 216], [185, 759]]}, {"instances": "tao", "configurations": 342, "value": [[682, 262], [276, 668]]}, {"instances": "tao", "configurations": 343, "value": [[691, 253], [121, 823]]}, {"instances": "tao", "configurations": 344, "value": [[732, 212], [214, 730]]}, {"instances": "tao", "configurations": 345, "value": [[719, 225], [145, 799]]}, {"instances": "tao", "configurations": 346, "value": [[740, 204], [180, 764]]}, {"instances": "tao", "configurations": 347, "value": [[701, 243], [131, 813]]}, {"instances": "tao", "configurations": 348, "value": [[736, 208], [179, 765]]}, {"instances": "tao", "configurations": 349, "value": [[731, 213], [199, 745]]}, {"instances": "tao", "configurations": 350, "value": [[662, 282], [104, 840]]}, {"instances": "tao", "configurations": 351, "value": [[716, 228], [163, 781]]}, {"instances": "tao", "configurations": 352, "value": [[736, 208], [185, 759]]}, {"instances": "tao", "configurations": 353, "value": [[743, 201], [184, 760]]}, {"instances": "tao", "configurations": 354, "value": [[735, 209], [178, 766]]}, {"instances": "tao", "configurations": 355, "value": [[717, 227], [96, 848]]}, {"instances": "tao", "configurations": 356, "value": [[735, 209], [207, 737]]}, {"instances": "tao", "configurations": 357, "value": [[727, 217], [135, 809]]}, {"instances": "tao", "configurations": 358, "value": [[726, 218], [183, 761]]}, {"instances": "tao", "configurations": 359, "value": [[705, 239], [221, 723]]}, {"instances": "tao", "configurations": 360, "value": [[727, 217], [205, 739]]}, {"instances": "tao", "configurations": 361, "value": [[740, 204], [196, 748]]}, {"instances": "tao", "configurations": 362, "value": [[743, 201], [162, 782]]}, {"instances": "tao", "configurations": 363, "value": [[743, 201], [161, 783]]}, {"instances": "tao", "configurations": 364, "value": [[723, 221], [139, 805]]}, {"instances": "tao", "configurations": 365, "value": [[851, 93], [191, 753]]}, {"instances": "tao", "configurations": 366, "value": [[733, 211], [194, 750]]}, {"instances": "tao", "configurations": 367, "value": [[737, 207], [199, 745]]}, {"instances": "tao", "configurations": 368, "value": [[738, 206], [200, 744]]}, {"instances": "tao", "configurations": 369, "value": [[724, 220], [209, 735]]}, {"instances": "tao", "configurations": 370, "value": [[742, 202], [159, 785]]}, {"instances": "tao", "configurations": 371, "value": [[689, 255], [122, 822]]}, {"instances": "tao", "configurations": 372, "value": [[726, 218], [202, 742]]}, {"instances": "tao", "configurations": 373, "value": [[162, 782], [830, 114]]}, {"instances": "tao", "configurations": 374, "value": [[664, 280], [274, 670]]}, {"instances": "tao", "configurations": 375, "value": [[730, 214], [278, 666]]}, {"instances": "tao", "configurations": 376, "value": [[747, 197], [174, 770]]}, {"instances": "tao", "configurations": 377, "value": [[797, 147], [292, 652]]}, {"instances": "tao", "configurations": 378, "value": [[729, 215], [179, 765]]}, {"instances": "tao", "configurations": 379, "value": [[729, 215], [197, 747]]}, {"instances": "tao", "configurations": 380, "value": [[730, 214], [185, 759]]}, {"instances": "tao", "configurations": 381, "value": [[551, 393], [161, 783]]}, {"instances": "tao", "configurations": 382, "value": [[728, 216], [195, 749]]}, {"instances": "tao", "configurations": 383, "value": [[129, 815], [814, 130]]}, {"instances": "tao", "configurations": 384, "value": [[735, 209], [158, 786]]}, {"instances": "tao", "configurations": 385, "value": [[738, 206], [241, 703]]}, {"instances": "tao", "configurations": 386, "value": [[654, 290], [215, 729]]}, {"instances": "tao", "configurations": 387, "value": [[729, 215], [213, 731]]}, {"instances": "tao", "configurations": 388, "value": [[703, 241], [262, 682]]}, {"instances": "tao", "configurations": 389, "value": [[726, 218], [216, 728]]}, {"instances": "tao", "configurations": 390, "value": [[620, 324], [163, 781]]}, {"instances": "tao", "configurations": 391, "value": [[726, 218], [218, 726]]}, {"instances": "tao", "configurations": 392, "value": [[725, 219], [203, 741]]}, {"instances": "tao", "configurations": 393, "value": [[580, 364], [152, 792]]}, {"instances": "tao", "configurations": 394, "value": [[731, 213], [210, 734]]}, {"instances": "tao", "configurations": 395, "value": [[721, 223], [213, 731]]}, {"instances": "tao", "configurations": 396, "value": [[723, 221], [230, 714]]}, {"instances": "tao", "configurations": 397, "value": [[667, 277], [264, 680]]}, {"instances": "tao", "configurations": 398, "value": [[716, 228], [163, 781]]}, {"instances": "tao", "configurations": 399, "value": [[753, 191], [239, 705]]}, {"instances": "tao", "configurations": 400, "value": [[728, 216], [207, 737]]}, {"instances": "tao", "configurations": 401, "value": [[731, 213], [211, 733]]}, {"instances": "tao", "configurations": 402, "value": [[708, 236], [207, 737]]}, {"instances": "tao", "configurations": 403, "value": [[696, 248], [170, 774]]}, {"instances": "tao", "configurations": 404, "value": [[640, 304], [322, 622]]}, {"instances": "tao", "configurations": 405, "value": [[728, 216], [254, 690]]}, {"instances": "tao", "configurations": 406, "value": [[732, 212], [212, 732]]}, {"instances": "tao", "configurations": 407, "value": [[831, 113], [261, 683]]}, {"instances": "tao", "configurations": 408, "value": [[734, 210], [196, 748]]}, {"instances": "tao", "configurations": 409, "value": [[669, 275], [151, 793]]}, {"instances": "tao", "configurations": 410, "value": [[716, 228], [221, 723]]}, {"instances": "tao", "configurations": 411, "value": [[688, 256], [419, 525]]}, {"instances": "tao", "configurations": 412, "value": [[713, 231], [235, 709]]}, {"instances": "tao", "configurations": 413, "value": [[727, 217], [203, 741]]}, {"instances": "tao", "configurations": 414, "value": [[344, 600], [540, 404]]}, {"instances": "tao", "configurations": 415, "value": [[760, 184], [269, 675]]}, {"instances": "tao", "configurations": 416, "value": [[656, 288], [192, 752]]}, {"instances": "tao", "configurations": 417, "value": [[725, 219], [206, 738]]}, {"instances": "tao", "configurations": 418, "value": [[650, 294], [283, 661]]}, {"instances": "tao", "configurations": 419, "value": [[719, 225], [206, 738]]}, {"instances": "tao", "configurations": 420, "value": [[731, 213], [184, 760]]}, {"instances": "tao", "configurations": 421, "value": [[766, 178], [226, 718]]}, {"instances": "tao", "configurations": 422, "value": [[735, 209], [195, 749]]}, {"instances": "tao", "configurations": 423, "value": [[714, 230], [191, 753]]}, {"instances": "tao", "configurations": 424, "value": [[725, 219], [189, 755]]}, {"instances": "tao", "configurations": 425, "value": [[681, 263], [47, 897]]}, {"instances": "tao", "configurations": 426, "value": [[730, 214], [192, 752]]}, {"instances": "tao", "configurations": 427, "value": [[647, 297], [90, 854]]}, {"instances": "tao", "configurations": 428, "value": [[785, 159], [92, 852]]}, {"instances": "tao", "configurations": 429, "value": [[518, 426], [433, 511]]}, {"instances": "tao", "configurations": 430, "value": [[667, 277], [265, 679]]}, {"instances": "tao", "configurations": 431, "value": [[731, 213], [197, 747]]}, {"instances": "tao", "configurations": 432, "value": [[733, 211], [205, 739]]}, {"instances": "tao", "configurations": 433, "value": [[728, 216], [203, 741]]}, {"instances": "tao", "configurations": 434, "value": [[606, 338], [97, 847]]}, {"instances": "tao", "configurations": 435, "value": [[736, 208], [183, 761]]}, {"instances": "tao", "configurations": 436, "value": [[731, 213], [208, 736]]}, {"instances": "tao", "configurations": 437, "value": [[731, 213], [213, 731]]}, {"instances": "tao", "configurations": 438, "value": [[724, 220], [208, 736]]}, {"instances": "tao", "configurations": 439, "value": [[729, 215], [199, 745]]}, {"instances": "tao", "configurations": 440, "value": [[750, 194], [177, 767]]}, {"instances": "tao", "configurations": 441, "value": [[728, 216], [210, 734]]}, {"instances": "tao", "configurations": 442, "value": [[694, 250], [149, 795]]}, {"instances": "tao", "configurations": 443, "value": [[744, 200], [173, 771]]}, {"instances": "tao", "configurations": 444, "value": [[733, 211], [280, 664]]}, {"instances": "tao", "configurations": 445, "value": [[740, 204], [175, 769]]}, {"instances": "tao", "configurations": 446, "value": [[732, 212], [209, 735]]}, {"instances": "tao", "configurations": 447, "value": [[743, 201], [163, 781]]}, {"instances": "tao", "configurations": 448, "value": [[742, 202], [176, 768]]}, {"instances": "tao", "configurations": 449, "value": [[730, 214], [195, 749]]}, {"instances": "tao", "configurations": 450, "value": [[737, 207], [214, 730]]}, {"instances": "tao", "configurations": 451, "value": [[738, 206], [155, 789]]}, {"instances": "tao", "configurations": 452, "value": [[733, 211], [186, 758]]}, {"instances": "tao", "configurations": 453, "value": [[700, 244], [159, 785]]}, {"instances": "tao", "configurations": 454, "value": [[736, 208], [223, 721]]}, {"instances": "tao", "configurations": 455, "value": [[688, 256], [121, 823]]}, {"instances": "tao", "configurations": 456, "value": [[725, 219], [137, 807]]}, {"instances": "tao", "configurations": 457, "value": [[686, 258], [140, 804]]}, {"instances": "tao", "configurations": 458, "value": [[720, 224], [155, 789]]}, {"instances": "tao", "configurations": 459, "value": [[746, 198], [182, 762]]}, {"instances": "tao", "configurations": 460, "value": [[732, 212], [193, 751]]}, {"instances": "tao", "configurations": 461, "value": [[739, 205], [193, 751]]}, {"instances": "tao", "configurations": 462, "value": [[719, 225], [149, 795]]}, {"instances": "tao", "configurations": 463, "value": [[730, 214], [211, 733]]}, {"instances": "tao", "configurations": 464, "value": [[730, 214], [205, 739]]}, {"instances": "tao", "configurations": 465, "value": [[748, 196], [176, 768]]}, {"instances": "tao", "configurations": 466, "value": [[714, 230], [176, 768]]}, {"instances": "tao", "configurations": 467, "value": [[739, 205], [181, 763]]}, {"instances": "tao", "configurations": 468, "value": [[745, 199], [174, 770]]}, {"instances": "tao", "configurations": 469, "value": [[694, 250], [300, 644]]}, {"instances": "tao", "configurations": 470, "value": [[690, 254], [120, 824]]}, {"instances": "tao", "configurations": 471, "value": [[662, 282], [215, 729]]}, {"instances": "tao", "configurations": 472, "value": [[725, 219], [219, 725]]}, {"instances": "tao", "configurations": 473, "value": [[736, 208], [213, 731]]}, {"instances": "tao", "configurations": 474, "value": [[733, 211], [194, 750]]}, {"instances": "tao", "configurations": 475, "value": [[736, 208], [178, 766]]}, {"instances": "tao", "configurations": 476, "value": [[728, 216], [201, 743]]}, {"instances": "tao", "configurations": 477, "value": [[717, 227], [138, 806]]}, {"instances": "tao", "configurations": 478, "value": [[743, 201], [179, 765]]}, {"instances": "tao", "configurations": 479, "value": [[743, 201], [162, 782]]}, {"instances": "tao", "configurations": 480, "value": [[734, 210], [213, 731]]}, {"instances": "tao", "configurations": 481, "value": [[722, 222], [247, 697]]}, {"instances": "tao", "configurations": 482, "value": [[726, 218], [191, 753]]}, {"instances": "tao", "configurations": 483, "value": [[741, 203], [173, 771]]}, {"instances": "tao", "configurations": 484, "value": [[701, 243], [155, 789]]}, {"instances": "tao", "configurations": 485, "value": [[696, 248], [122, 822]]}, {"instances": "tao", "configurations": 486, "value": [[713, 231], [126, 818]]}, {"instances": "tao", "configurations": 487, "value": [[753, 191], [202, 742]]}, {"instances": "tao", "configurations": 488, "value": [[728, 216], [140, 804]]}, {"instances": "tao", "configurations": 489, "value": [[700, 244], [119, 825]]}, {"instances": "tao", "configurations": 490, "value": [[733, 211], [147, 797]]}, {"instances": "tao", "configurations": 491, "value": [[734, 210], [186, 758]]}, {"instances": "tao", "configurations": 492, "value": [[729, 215], [218, 726]]}, {"instances": "tao", "configurations": 493, "value": [[728, 216], [213, 731]]}, {"instances": "tao", "configurations": 494, "value": [[750, 194], [177, 767]]}, {"instances": "tao", "configurations": 495, "value": [[728, 216], [206, 738]]}, {"instances": "tao", "configurations": 496, "value": [[702, 242], [192, 752]]}, {"instances": "tao", "configurations": 497, "value": [[731, 213], [214, 730]]}, {"instances": "tao", "configurations": 498, "value": [[736, 208], [220, 724]]}, {"instances": "tao", "configurations": 499, "value": [[705, 239], [244, 700]]}, {"instances": "tao", "configurations": 500, "value": [[729, 215], [212, 732]]}, {"instances": "tao", "configurations": 501, "value": [[731, 213], [209, 735]]}, {"instances": "tao", "configurations": 502, "value": [[730, 214], [209, 735]]}, {"instances": "tao", "configurations": 503, "value": [[742, 202], [175, 769]]}, {"instances": "tao", "configurations": 504, "value": [[708, 236], [207, 737]]}, {"instances": "tao", "configurations": 505, "value": [[727, 217], [203, 741]]}, {"instances": "tao", "configurations": 506, "value": [[745, 199], [178, 766]]}, {"instances": "tao", "configurations": 507, "value": [[743, 201], [163, 781]]}, {"instances": "tao", "configurations": 508, "value": [[727, 217], [201, 743]]}, {"instances": "tao", "configurations": 509, "value": [[862, 82], [347, 597]]}, {"instances": "tao", "configurations": 510, "value": [[706, 238], [177, 767]]}, {"instances": "tao", "configurations": 511, "value": [[779, 165], [200, 744]]}, {"instances": "tao", "configurations": 512, "value": [[732, 212], [210, 734]]}, {"instances": "tao", "configurations": 513, "value": [[730, 214], [210, 734]]}, {"instances": "tao", "configurations": 514, "value": [[689, 255], [230, 714]]}, {"instances": "tao", "configurations": 515, "value": [[728, 216], [209, 735]]}, {"instances": "tao", "configurations": 516, "value": [[716, 228], [224, 720]]}, {"instances": "tao", "configurations": 517, "value": [[747, 197], [199, 745]]}, {"instances": "tao", "configurations": 518, "value": [[655, 289], [245, 699]]}, {"instances": "tao", "configurations": 519, "value": [[696, 248], [170, 774]]}, {"instances": "tao", "configurations": 520, "value": [[668, 276], [170, 774]]}, {"instances": "tao", "configurations": 521, "value": [[727, 217], [205, 739]]}, {"instances": "tao", "configurations": 522, "value": [[739, 205], [210, 734]]}, {"instances": "tao", "configurations": 523, "value": [[730, 214], [203, 741]]}, {"instances": "tao", "configurations": 524, "value": [[685, 259], [177, 767]]}, {"instances": "tao", "configurations": 525, "value": [[718, 226], [201, 743]]}, {"instances": "tao", "configurations": 526, "value": [[826, 118], [268, 676]]}, {"instances": "tao", "configurations": 527, "value": [[729, 215], [211, 733]]}, {"instances": "tao", "configurations": 528, "value": [[521, 423], [562, 382]]}, {"instances": "tao", "configurations": 529, "value": [[669, 275], [278, 666]]}, {"instances": "tao", "configurations": 530, "value": [[768, 176], [297, 647]]}, {"instances": "tao", "configurations": 531, "value": [[704, 240], [164, 780]]}, {"instances": "tao", "configurations": 532, "value": [[847, 97], [275, 669]]}, {"instances": "tao", "configurations": 533, "value": [[683, 261], [370, 574]]}, {"instances": "tao", "configurations": 534, "value": [[509, 435], [204, 740]]}, {"instances": "tao", "configurations": 535, "value": [[702, 242], [82, 862]]}, {"instances": "tao", "configurations": 536, "value": [[738, 206], [196, 748]]}, {"instances": "tao", "configurations": 537, "value": [[742, 202], [163, 781]]}, {"instances": "tao", "configurations": 538, "value": [[752, 192], [215, 729]]}, {"instances": "tao", "configurations": 539, "value": [[739, 205], [182, 762]]}, {"instances": "tao", "configurations": 540, "value": [[719, 225], [212, 732]]}, {"instances": "tao", "configurations": 541, "value": [[699, 245], [120, 824]]}, {"instances": "tao", "configurations": 542, "value": [[737, 207], [177, 767]]}, {"instances": "tao", "configurations": 543, "value": [[727, 217], [202, 742]]}, {"instances": "tao", "configurations": 544, "value": [[736, 208], [151, 793]]}, {"instances": "tao", "configurations": 545, "value": [[730, 214], [140, 804]]}, {"instances": "tao", "configurations": 546, "value": [[725, 219], [211, 733]]}, {"instances": "tao", "configurations": 547, "value": [[710, 234], [124, 820]]}, {"instances": "tao", "configurations": 548, "value": [[798, 146], [224, 720]]}, {"instances": "tao", "configurations": 549, "value": [[556, 388], [144, 800]]}, {"instances": "tao", "configurations": 550, "value": [[662, 282], [105, 839]]}, {"instances": "tao", "configurations": 551, "value": [[721, 223], [225, 719]]}, {"instances": "tao", "configurations": 552, "value": [[668, 276], [170, 774]]}, {"instances": "tao", "configurations": 553, "value": [[710, 234], [199, 745]]}, {"instances": "tao", "configurations": 554, "value": [[673, 271], [327, 617]]}, {"instances": "tao", "configurations": 555, "value": [[743, 201], [173, 771]]}, {"instances": "tao", "configurations": 556, "value": [[730, 214], [164, 780]]}, {"instances": "tao", "configurations": 557, "value": [[716, 228], [192, 752]]}, {"instances": "tao", "configurations": 558, "value": [[222, 722], [764, 180]]}, {"instances": "tao", "configurations": 559, "value": [[733, 211], [209, 735]]}, {"instances": "tao", "configurations": 560, "value": [[737, 207], [207, 737]]}, {"instances": "tao", "configurations": 561, "value": [[743, 201], [166, 778]]}, {"instances": "tao", "configurations": 562, "value": [[701, 243], [145, 799]]}, {"instances": "tao", "configurations": 563, "value": [[724, 220], [131, 813]]}, {"instances": "tao", "configurations": 564, "value": [[746, 198], [178, 766]]}, {"instances": "tao", "configurations": 565, "value": [[739, 205], [196, 748]]}, {"instances": "tao", "configurations": 566, "value": [[730, 214], [212, 732]]}, {"instances": "tao", "configurations": 567, "value": [[747, 197], [177, 767]]}, {"instances": "tao", "configurations": 568, "value": [[738, 206], [176, 768]]}, {"instances": "tao", "configurations": 569, "value": [[692, 252], [295, 649]]}, {"instances": "tao", "configurations": 570, "value": [[730, 214], [197, 747]]}, {"instances": "tao", "configurations": 571, "value": [[695, 249], [124, 820]]}, {"instances": "tao", "configurations": 572, "value": [[739, 205], [196, 748]]}, {"instances": "tao", "configurations": 573, "value": [[695, 249], [120, 824]]}, {"instances": "tao", "configurations": 574, "value": [[658, 286], [241, 703]]}, {"instances": "tao", "configurations": 575, "value": [[734, 210], [187, 757]]}, {"instances": "tao", "configurations": 576, "value": [[130, 814], [810, 134]]}, {"instances": "tao", "configurations": 577, "value": [[737, 207], [182, 762]]}, {"instances": "tao", "configurations": 578, "value": [[740, 204], [187, 757]]}, {"instances": "tao", "configurations": 579, "value": [[741, 203], [158, 786]]}, {"instances": "tao", "configurations": 580, "value": [[735, 209], [213, 731]]}, {"instances": "tao", "configurations": 581, "value": [[734, 210], [184, 760]]}, {"instances": "tao", "configurations": 582, "value": [[742, 202], [165, 779]]}, {"instances": "tao", "configurations": 583, "value": [[750, 194], [263, 681]]}, {"instances": "tao", "configurations": 584, "value": [[734, 210], [172, 772]]}, {"instances": "tao", "configurations": 585, "value": [[714, 230], [133, 811]]}, {"instances": "tao", "configurations": 586, "value": [[730, 214], [197, 747]]}, {"instances": "tao", "configurations": 587, "value": [[740, 204], [193, 751]]}, {"instances": "tao", "configurations": 588, "value": [[738, 206], [199, 745]]}, {"instances": "tao", "configurations": 589, "value": [[732, 212], [212, 732]]}, {"instances": "tao", "configurations": 590, "value": [[646, 298], [265, 679]]}, {"instances": "tao", "configurations": 591, "value": [[716, 228], [154, 790]]}, {"instances": "tao", "configurations": 592, "value": [[731, 213], [204, 740]]}, {"instances": "tao", "configurations": 593, "value": [[732, 212], [193, 751]]}, {"instances": "tao", "configurations": 594, "value": [[780, 164], [273, 671]]}, {"instances": "tao", "configurations": 595, "value": [[732, 212], [197, 747]]}, {"instances": "tao", "configurations": 596, "value": [[732, 212], [195, 749]]}, {"instances": "tao", "configurations": 597, "value": [[679, 265], [218, 726]]}, {"instances": "tao", "configurations": 598, "value": [[759, 185], [286, 658]]}, {"instances": "tao", "configurations": 599, "value": [[706, 238], [379, 565]]}, {"instances": "tao", "configurations": 600, "value": [[733, 211], [211, 733]]}, {"instances": "tao", "configurations": 601, "value": [[743, 201], [179, 765]]}, {"instances": "tao", "configurations": 602, "value": [[732, 212], [196, 748]]}, {"instances": "tao", "configurations": 603, "value": [[731, 213], [197, 747]]}, {"instances": "tao", "configurations": 604, "value": [[846, 98], [319, 625]]}, {"instances": "tao", "configurations": 605, "value": [[727, 217], [204, 740]]}, {"instances": "tao", "configurations": 606, "value": [[735, 209], [211, 733]]}, {"instances": "tao", "configurations": 607, "value": [[738, 206], [197, 747]]}, {"instances": "tao", "configurations": 608, "value": [[732, 212], [211, 733]]}, {"instances": "tao", "configurations": 609, "value": [[738, 206], [201, 743]]}, {"instances": "tao", "configurations": 610, "value": [[729, 215], [213, 731]]}, {"instances": "tao", "configurations": 611, "value": [[730, 214], [200, 744]]}, {"instances": "tao", "configurations": 612, "value": [[731, 213], [204, 740]]}, {"instances": "tao", "configurations": 613, "value": [[739, 205], [182, 762]]}, {"instances": "tao", "configurations": 614, "value": [[735, 209], [190, 754]]}, {"instances": "tao", "configurations": 615, "value": [[736, 208], [183, 761]]}, {"instances": "tao", "configurations": 616, "value": [[724, 220], [215, 729]]}, {"instances": "tao", "configurations": 617, "value": [[741, 203], [181, 763]]}, {"instances": "tao", "configurations": 618, "value": [[736, 208], [187, 757]]}, {"instances": "tao", "configurations": 619, "value": [[778, 166], [273, 671]]}, {"instances": "tao", "configurations": 620, "value": [[735, 209], [190, 754]]}, {"instances": "tao", "configurations": 621, "value": [[730, 214], [201, 743]]}, {"instances": "tao", "configurations": 622, "value": [[731, 213], [204, 740]]}, {"instances": "tao", "configurations": 623, "value": [[733, 211], [196, 748]]}, {"instances": "tao", "configurations": 624, "value": [[730, 214], [197, 747]]}, {"instances": "tao", "configurations": 625, "value": [[727, 217], [201, 743]]}, {"instances": "tao", "configurations": 626, "value": [[730, 214], [199, 745]]}, {"instances": "tao", "configurations": 627, "value": [[666, 278], [221, 723]]}, {"instances": "tao", "configurations": 628, "value": [[730, 214], [197, 747]]}, {"instances": "tao", "configurations": 629, "value": [[733, 211], [195, 749]]}, {"instances": "tao", "configurations": 630, "value": [[726, 218], [204, 740]]}, {"instances": "tao", "configurations": 631, "value": [[731, 213], [196, 748]]}, {"instances": "tao", "configurations": 632, "value": [[719, 225], [230, 714]]}, {"instances": "tao", "configurations": 633, "value": [[553, 391], [116, 828]]}, {"instances": "tao", "configurations": 634, "value": [[137, 807], [814, 130]]}, {"instances": "tao", "configurations": 635, "value": [[729, 215], [164, 780]]}, {"instances": "tao", "configurations": 636, "value": [[659, 285], [216, 728]]}, {"instances": "tao", "configurations": 637, "value": [[743, 201], [241, 703]]}, {"instances": "tao", "configurations": 638, "value": [[731, 213], [199, 745]]}, {"instances": "tao", "configurations": 639, "value": [[741, 203], [195, 749]]}, {"instances": "tao", "configurations": 640, "value": [[733, 211], [196, 748]]}, {"instances": "tao", "configurations": 641, "value": [[611, 333], [125, 819]]}, {"instances": "tao", "configurations": 642, "value": [[753, 191], [149, 795]]}, {"instances": "tao", "configurations": 643, "value": [[730, 214], [195, 749]]}, {"instances": "tao", "configurations": 644, "value": [[732, 212], [211, 733]]}, {"instances": "tao", "configurations": 645, "value": [[731, 213], [213, 731]]}, {"instances": "tao", "configurations": 646, "value": [[754, 190], [297, 647]]}, {"instances": "tao", "configurations": 647, "value": [[728, 216], [217, 727]]}, {"instances": "tao", "configurations": 648, "value": [[776, 168], [280, 664]]}, {"instances": "tao", "configurations": 649, "value": [[784, 160], [328, 616]]}, {"instances": "tao", "configurations": 650, "value": [[730, 214], [198, 746]]}, {"instances": "tao", "configurations": 651, "value": [[735, 209], [190, 754]]}, {"instances": "tao", "configurations": 652, "value": [[740, 204], [198, 746]]}, {"instances": "tao", "configurations": 653, "value": [[726, 218], [201, 743]]}, {"instances": "tao", "configurations": 654, "value": [[731, 213], [205, 739]]}, {"instances": "tao", "configurations": 655, "value": [[731, 213], [196, 748]]}, {"instances": "tao", "configurations": 656, "value": [[135, 809], [810, 134]]}, {"instances": "tao", "configurations": 657, "value": [[728, 216], [202, 742]]}, {"instances": "tao", "configurations": 658, "value": [[134, 810], [810, 134]]}, {"instances": "tao", "configurations": 659, "value": [[134, 810], [810, 134]]}, {"instances": "tao", "configurations": 660, "value": [[410, 534], [543, 401]]}, {"instances": "tao", "configurations": 661, "value": [[729, 215], [200, 744]]}, {"instances": "tao", "configurations": 662, "value": [[142, 802], [806, 138]]}, {"instances": "tao", "configurations": 663, "value": [[134, 810], [808, 136]]}, {"instances": "tao", "configurations": 664, "value": [[672, 272], [229, 715]]}, {"instances": "tao", "configurations": 665, "value": [[729, 215], [191, 753]]}, {"instances": "tao", "configurations": 666, "value": [[731, 213], [199, 745]]}]